{"info":{"FIRST_NAME":"Wallace","LAST_NAME":"Jones","WEIGHT":"225","COUNTRY":"USA","SCHOOL":"Kentucky","BIRTHDATE":"1926-07-14T00:00:00","HEIGHT":"6-4","TO_YEAR":1951,"DLEAGUE":"N","FROM_YEAR":1949,"TEAM":"INO","PERSON_ID":77199,"SEASON_EXP":2,"POSITION":"Forward","ROSTERSTATUS":"Active","ALL_STAR":0,"PIE":0,"JERSEY":""},"career":{"header":["MIN","FGM","FGA","FG_PCT","FG3M","FG3A","FG3_PCT","FTM","FTA","FT_PCT","OREB","DREB","REB","AST","STL","BLK","TOV","PF","PTS"],"RegularSeason":{"PerGame":[9.4,3.7,10.5,0.355,null,null,null,2.8,3.6,0.757,null,null,2.9,3.1,null,null,null,3.2,10.2],"GS":null,"GP":140},"PostSeason":{"PerGame":[1.3,3.8,12.7,0.303,null,null,null,4.8,5.7,0.853,null,null,0.0,3.7,null,null,null,4.7,12.5],"GS":null,"GP":6}},"season":{"PostSeason":{"1949":{"GameList":{"44900252":[77199,"0044900252","03/23/1950","INO","Olympians","SHE","Redskins",0,20,0,0,0,0,0,0,0,0,0],"44900253":[77199,"0044900253","03/25/1950","INO","Olympians","SHE","Redskins",0,11,0,0,0,0,0,0,0,0,0],"44900251":[77199,"0044900251","03/21/1950","INO","Olympians","SHE","Redskins",0,12,0,0,0,0,0,0,0,0,0],"44900323":[77199,"0044900323","04/01/1950","INO","Olympians","AND","Packers",0,13,0,0,0,0,0,0,0,0,0],"44900321":[77199,"0044900321","03/28/1950","INO","Olympians","AND","Packers",0,17,0,0,0,0,0,0,0,0,0]},"data":[23.0,5,null,null,4.4,14.6,0.301,null,null,null,5.8,6.8,0.853,null,null,null,4.4,null,null,null,5.2,14.6],"rank":{},"team":"INO"},"1951":{"GameList":{"45100212":[77199,"0045100212","03/25/1952","INO","Olympians","MNL","Lakers",0,2,0,0,0,0,0,0,0,0,0]},"data":[25.0,1,null,8.0,1.0,3.0,0.333,null,null,null,0.0,0.0,null,null,null,0.0,0.0,null,null,null,2.0,2.0],"rank":{"PerGame":[null,null,null,null,null,null,null,null,null,null,null,null,null,null,null,null,null,null,null],"Totals":[70,65,68,null,null,null,null,68,68,null,null,null,71,72,null,null,null,69,1]},"team":"INO"}},"headerGame":["PLAYER_ID","GAME_ID","GAME_DATE","TEAM_ABBREVIATION","TEAM_NAME","VS_TEAM_ABBREVIATION","VS_TEAM_NAME","TOV","PTS","FGM","FGA","FG3M","FG3A","PF","BLK","STL","AST","REB"],"headerData":["PLAYER_AGE","GP","GS","MIN","FGM","FGA","FG_PCT","FG3M","FG3A","FG3_PCT","FTM","FTA","FT_PCT","OREB","DREB","REB","AST","STL","BLK","TOV","PF","PTS"],"RegularSeason":{"1949":{"GameList":{"24900091":[77199,"0024900091","11/23/1949","INO","Olympians","CHS","Stags",0,22,0,0,0,0,0,0,0,0,0],"24900547":[77199,"0024900547","03/16/1950","INO","Olympians","DN","Nuggets",0,22,0,0,0,0,0,0,0,0,0],"24900302":[77199,"0024900302","01/15/1950","INO","Olympians","SYR","Nationals",0,10,0,0,0,0,0,0,0,0,0],"24900280":[77199,"0024900280","01/10/1950","INO","Olympians","SHE","Redskins",0,3,0,0,0,0,0,0,0,0,0],"24900171":[77199,"0024900171","12/13/1949","INO","Olympians","TCB","Blackhawks",0,15,0,0,0,0,0,0,0,0,0],"24900225":[77199,"0024900225","12/27/1949","INO","Olympians","AND","Packers",0,8,0,0,0,0,0,0,0,0,0],"24900115":[77199,"0024900115","11/29/1949","INO","Olympians","TCB","Blackhawks",0,7,0,0,0,0,0,0,0,0,0],"24900037":[77199,"0024900037","11/10/1949","INO","Olympians","NYK","Knicks",0,9,0,0,0,0,0,0,0,0,0],"24900272":[77199,"0024900272","01/07/1950","INO","Olympians","BAL","Bullets",0,10,0,0,0,0,0,0,0,0,0],"24900031":[77199,"0024900031","11/09/1949","INO","Olympians","SYR","Nationals",0,6,0,0,0,0,0,0,0,0,0],"24900496":[77199,"0024900496","03/03/1950","INO","Olympians","TCB","Blackhawks",0,32,0,0,0,0,0,0,0,0,0],"24900206":[77199,"0024900206","12/22/1949","INO","Olympians","CHS","Stags",0,3,0,0,0,0,0,0,0,0,0],"24900157":[77199,"0024900157","12/09/1949","INO","Olympians","DN","Nuggets",0,6,0,0,0,0,0,0,0,0,0],"24900362":[77199,"0024900362","01/30/1950","INO","Olympians","SYR","Nationals",0,7,0,0,0,0,0,0,0,0,0],"24900051":[77199,"0024900051","11/13/1949","INO","Olympians","SHE","Redskins",0,19,0,0,0,0,0,0,0,0,0],"24900307":[77199,"0024900307","01/17/1950","INO","Olympians","DN","Nuggets",0,10,0,0,0,0,0,0,0,0,0],"24900323":[77199,"0024900323","01/21/1950","INO","Olympians","FTW","Pistons",0,29,0,0,0,0,0,0,0,0,0],"24900247":[77199,"0024900247","01/01/1950","INO","Olympians","SHE","Redskins",0,18,0,0,0,0,0,0,0,0,0],"24900337":[77199,"0024900337","01/24/1950","INO","Olympians","WAT","Hawks",0,2,0,0,0,0,0,0,0,0,0],"24900059":[77199,"0024900059","11/15/1949","INO","Olympians","AND","Packers",0,4,0,0,0,0,0,0,0,0,0],"24900197":[77199,"0024900197","12/20/1949","INO","Olympians","BAL","Bullets",0,4,0,0,0,0,0,0,0,0,0],"24900556":[77199,"0024900556","03/18/1950","INO","Olympians","DN","Nuggets",0,12,0,0,0,0,0,0,0,0,0],"24900532":[77199,"0024900532","03/12/1950","INO","Olympians","WAT","Hawks",0,6,0,0,0,0,0,0,0,0,0],"24900192":[77199,"0024900192","12/18/1949","INO","Olympians","DN","Nuggets",0,14,0,0,0,0,0,0,0,0,0],"24900472":[77199,"0024900472","02/26/1950","INO","Olympians","SHE","Redskins",0,6,0,0,0,0,0,0,0,0,0],"24900439":[77199,"0024900439","02/18/1950","INO","Olympians","WAS","Capitols",0,19,0,0,0,0,0,0,0,0,0],"24900076":[77199,"0024900076","11/19/1949","INO","Olympians","WAT","Hawks",0,9,0,0,0,0,0,0,0,0,0],"24900153":[77199,"0024900153","12/08/1949","INO","Olympians","AND","Packers",0,9,0,0,0,0,0,0,0,0,0],"24900392":[77199,"0024900392","02/05/1950","INO","Olympians","BOM","Bombers",0,18,0,0,0,0,0,0,0,0,0],"24900292":[77199,"0024900292","01/13/1950","INO","Olympians","WAT","Hawks",0,23,0,0,0,0,0,0,0,0,0],"24900396":[77199,"0024900396","02/07/1950","INO","Olympians","WAS","Capitols",0,18,0,0,0,0,0,0,0,0,0],"24900518":[77199,"0024900518","03/09/1950","INO","Olympians","AND","Packers",0,8,0,0,0,0,0,0,0,0,0],"24900143":[77199,"0024900143","12/06/1949","INO","Olympians","BOS","Celtics",0,11,0,0,0,0,0,0,0,0,0],"24900127":[77199,"0024900127","12/01/1949","INO","Olympians","MNL","Lakers",0,17,0,0,0,0,0,0,0,0,0],"24900028":[77199,"0024900028","11/08/1949","INO","Olympians","NYK","Knicks",0,10,0,0,0,0,0,0,0,0,0],"24900481":[77199,"0024900481","02/28/1950","INO","Olympians","SYR","Nationals",0,16,0,0,0,0,0,0,0,0,0],"24900105":[77199,"0024900105","11/26/1949","INO","Olympians","SHE","Redskins",0,11,0,0,0,0,0,0,0,0,0],"24900042":[77199,"0024900042","11/11/1949","INO","Olympians","PHW","Warriors",0,12,0,0,0,0,0,0,0,0,0],"24900351":[77199,"0024900351","01/27/1950","INO","Olympians","AND","Packers",0,23,0,0,0,0,0,0,0,0,0],"24900047":[77199,"0024900047","11/12/1949","INO","Olympians","BOM","Bombers",0,21,0,0,0,0,0,0,0,0,0],"24900088":[77199,"0024900088","11/22/1949","INO","Olympians","ROC","Royals",0,5,0,0,0,0,0,0,0,0,0],"24900214":[77199,"0024900214","12/25/1949","INO","Olympians","WAT","Hawks",0,13,0,0,0,0,0,0,0,0,0],"24900376":[77199,"0024900376","02/02/1950","INO","Olympians","SYR","Nationals",0,13,0,0,0,0,0,0,0,0,0],"24900165":[77199,"0024900165","12/11/1949","INO","Olympians","FTW","Pistons",0,10,0,0,0,0,0,0,0,0,0],"24900449":[77199,"0024900449","02/21/1950","INO","Olympians","SHE","Redskins",0,17,0,0,0,0,0,0,0,0,0],"24900314":[77199,"0024900314","01/19/1950","INO","Olympians","WAT","Hawks",0,11,0,0,0,0,0,0,0,0,0],"24900445":[77199,"0024900445","02/19/1950","INO","Olympians","SYR","Nationals",0,13,0,0,0,0,0,0,0,0,0],"24900069":[77199,"0024900069","11/17/1949","INO","Olympians","BOS","Celtics",0,10,0,0,0,0,0,0,0,0,0],"24900254":[77199,"0024900254","01/03/1950","INO","Olympians","TCB","Blackhawks",0,24,0,0,0,0,0,0,0,0,0],"24900080":[77199,"0024900080","11/20/1949","INO","Olympians","MNL","Lakers",0,18,0,0,0,0,0,0,0,0,0],"24900509":[77199,"0024900509","03/07/1950","INO","Olympians","AND","Packers",0,7,0,0,0,0,0,0,0,0,0],"24900465":[77199,"0024900465","02/24/1950","INO","Olympians","SYR","Nationals",0,13,0,0,0,0,0,0,0,0,0],"24900006":[77199,"0024900006","11/01/1949","INO","Olympians","DN","Nuggets",0,9,0,0,0,0,0,0,0,0,0],"24900353":[77199,"0024900353","01/28/1950","INO","Olympians","TCB","Blackhawks",0,13,0,0,0,0,0,0,0,0,0],"24900541":[77199,"0024900541","03/14/1950","INO","Olympians","SYR","Nationals",0,4,0,0,0,0,0,0,0,0,0],"24900182":[77199,"0024900182","12/16/1949","INO","Olympians","DN","Nuggets",0,13,0,0,0,0,0,0,0,0,0],"24900423":[77199,"0024900423","02/14/1950","INO","Olympians","PHW","Warriors",0,11,0,0,0,0,0,0,0,0,0],"24900408":[77199,"0024900408","02/10/1950","INO","Olympians","AND","Packers",0,12,0,0,0,0,0,0,0,0,0],"24900502":[77199,"0024900502","03/05/1950","INO","Olympians","SHE","Redskins",0,16,0,0,0,0,0,0,0,0,0],"24900426":[77199,"0024900426","02/15/1950","INO","Olympians","WAT","Hawks",0,10,0,0,0,0,0,0,0,0,0]},"data":[23.0,60,null,null,4.4,11.8,0.374,null,null,null,3.7,5.0,0.751,null,null,null,3.2,null,null,null,4.0,12.5],"rank":{"PerGame":[null,24,33,12,null,null,null,24,27,40,null,null,20,17,null,null,null,25,null],"Totals":[null,29,38,12,null,null,null,27,35,40,null,null,39,24,null,null,null,31,39]},"team":"INO"},"1951":{"GameList":{"25100088":[77199,"0025100088","12/07/1951","INO","Olympians","BAL","Bullets",0,13,0,0,0,0,0,0,0,0,0],"25100164":[77199,"0025100164","01/09/1952","INO","Olympians","MNL","Lakers",0,9,0,0,0,0,0,0,0,0,0],"25100184":[77199,"0025100184","01/18/1952","INO","Olympians","PHW","Warriors",0,0,0,0,0,0,0,0,0,0,0],"25100187":[77199,"0025100187","01/19/1952","INO","Olympians","BAL","Bullets",0,2,0,0,0,0,0,0,0,0,0],"25100188":[77199,"0025100188","01/20/1952","INO","Olympians","BOS","Celtics",0,22,0,0,0,0,0,0,0,0,0],"25100083":[77199,"0025100083","12/04/1951","INO","Olympians","SYR","Nationals",0,10,0,0,0,0,0,0,0,0,0],"25100218":[77199,"0025100218","02/01/1952","INO","Olympians","MNL","Lakers",0,14,0,0,0,0,0,0,0,0,0],"25100172":[77199,"0025100172","01/12/1952","INO","Olympians","NYK","Knicks",0,10,0,0,0,0,0,0,0,0,0],"25100266":[77199,"0025100266","02/19/1952","INO","Olympians","BOS","Celtics",0,3,0,0,0,0,0,0,0,0,0],"25100152":[77199,"0025100152","01/04/1952","INO","Olympians","NYK","Knicks",0,0,0,0,0,0,0,0,0,0,0],"25100026":[77199,"0025100026","11/11/1951","INO","Olympians","SYR","Nationals",0,3,0,0,0,0,0,0,0,0,0],"25100071":[77199,"0025100071","11/30/1951","INO","Olympians","BOS","Celtics",0,14,0,0,0,0,0,0,0,0,0],"25100213":[77199,"0025100213","01/30/1952","INO","Olympians","FTW","Pistons",0,0,0,0,0,0,0,0,0,0,0],"25100212":[77199,"0025100212","01/29/1952","INO","Olympians","NYK","Knicks",0,7,0,0,0,0,0,0,0,0,0],"25100174":[77199,"0025100174","01/13/1952","INO","Olympians","SYR","Nationals",0,5,0,0,0,0,0,0,0,0,0],"25100033":[77199,"0025100033","11/13/1951","INO","Olympians","MNL","Lakers",0,0,0,0,0,0,0,0,0,0,0],"25100079":[77199,"0025100079","12/02/1951","INO","Olympians","MIH","Hawks",0,10,0,0,0,0,0,0,0,0,0],"25100254":[77199,"0025100254","02/14/1952","INO","Olympians","BAL","Bullets",0,10,0,0,0,0,0,0,0,0,0],"25100037":[77199,"0025100037","11/16/1951","INO","Olympians","MIH","Hawks",0,19,0,0,0,0,0,0,0,0,0],"25100273":[77199,"0025100273","02/22/1952","INO","Olympians","MIH","Hawks",0,10,0,0,0,0,0,0,0,0,0],"25100309":[77199,"0025100309","03/07/1952","INO","Olympians","SYR","Nationals",0,3,0,0,0,0,0,0,0,0,0],"25100277":[77199,"0025100277","02/23/1952","INO","Olympians","MIH","Hawks",0,9,0,0,0,0,0,0,0,0,0],"25100016":[77199,"0025100016","11/04/1951","INO","Olympians","BOS","Celtics",0,2,0,0,0,0,0,0,0,0,0],"25100156":[77199,"0025100156","01/05/1952","INO","Olympians","MNL","Lakers",0,10,0,0,0,0,0,0,0,0,0],"25100022":[77199,"0025100022","11/10/1951","INO","Olympians","ROC","Royals",0,13,0,0,0,0,0,0,0,0,0],"25100296":[77199,"0025100296","03/02/1952","INO","Olympians","FTW","Pistons",0,3,0,0,0,0,0,0,0,0,0],"25100291":[77199,"0025100291","03/01/1952","INO","Olympians","MNL","Lakers",0,12,0,0,0,0,0,0,0,0,0],"25100119":[77199,"0025100119","12/21/1951","INO","Olympians","MIH","Hawks",0,13,0,0,0,0,0,0,0,0,0],"25100109":[77199,"0025100109","12/16/1951","INO","Olympians","SYR","Nationals",0,17,0,0,0,0,0,0,0,0,0],"25100099":[77199,"0025100099","12/11/1951","INO","Olympians","MNL","Lakers",0,7,0,0,0,0,0,0,0,0,0],"25100123":[77199,"0025100123","12/23/1951","INO","Olympians","BOS","Celtics",0,17,0,0,0,0,0,0,0,0,0],"25100196":[77199,"0025100196","01/22/1952","INO","Olympians","ROC","Royals",0,4,0,0,0,0,0,0,0,0,0],"25100135":[77199,"0025100135","12/29/1951","INO","Olympians","BAL","Bullets",0,6,0,0,0,0,0,0,0,0,0],"25100094":[77199,"0025100094","12/09/1951","INO","Olympians","MNL","Lakers",0,13,0,0,0,0,0,0,0,0,0],"25100237":[77199,"0025100237","02/08/1952","INO","Olympians","MIH","Hawks",0,1,0,0,0,0,0,0,0,0,0],"25100178":[77199,"0025100178","01/15/1952","INO","Olympians","PHW","Warriors",0,0,0,0,0,0,0,0,0,0,0],"25100207":[77199,"0025100207","01/27/1952","INO","Olympians","ROC","Royals",0,2,0,0,0,0,0,0,0,0,0],"25100202":[77199,"0025100202","01/26/1952","INO","Olympians","NYK","Knicks",0,6,0,0,0,0,0,0,0,0,0],"25100144":[77199,"0025100144","12/31/1951","INO","Olympians","ROC","Royals",0,3,0,0,0,0,0,0,0,0,0],"25100201":[77199,"0025100201","01/25/1952","INO","Olympians","FTW","Pistons",0,8,0,0,0,0,0,0,0,0,0],"25100048":[77199,"0025100048","11/20/1951","INO","Olympians","ROC","Royals",0,9,0,0,0,0,0,0,0,0,0],"25100229":[77199,"0025100229","02/05/1952","INO","Olympians","PHW","Warriors",0,2,0,0,0,0,0,0,0,0,0],"25100255":[77199,"0025100255","02/15/1952","INO","Olympians","PHW","Warriors",0,4,0,0,0,0,0,0,0,0,0],"25100168":[77199,"0025100168","01/11/1952","INO","Olympians","BOS","Celtics",0,13,0,0,0,0,0,0,0,0,0],"25100227":[77199,"0025100227","02/03/1952","INO","Olympians","FTW","Pistons",0,5,0,0,0,0,0,0,0,0,0],"25100162":[77199,"0025100162","01/08/1952","INO","Olympians","MNL","Lakers",0,13,0,0,0,0,0,0,0,0,0],"25100107":[77199,"0025100107","12/15/1951","INO","Olympians","ROC","Royals",0,5,0,0,0,0,0,0,0,0,0],"25100160":[77199,"0025100160","01/06/1952","INO","Olympians","FTW","Pistons",0,4,0,0,0,0,0,0,0,0,0],"25100260":[77199,"0025100260","02/17/1952","INO","Olympians","ROC","Royals",0,6,0,0,0,0,0,0,0,0,0],"25100247":[77199,"0025100247","02/12/1952","INO","Olympians","FTW","Pistons",0,1,0,0,0,0,0,0,0,0,0],"25100062":[77199,"0025100062","11/25/1951","INO","Olympians","MNL","Lakers",0,5,0,0,0,0,0,0,0,0,0],"25100127":[77199,"0025100127","12/25/1951","INO","Olympians","ROC","Royals",0,10,0,0,0,0,0,0,0,0,0],"25100104":[77199,"0025100104","12/14/1951","INO","Olympians","NYK","Knicks",0,9,0,0,0,0,0,0,0,0,0],"25100240":[77199,"0025100240","02/09/1952","INO","Olympians","MIH","Hawks",0,0,0,0,0,0,0,0,0,0,0],"25100021":[77199,"0025100021","11/09/1951","INO","Olympians","FTW","Pistons",0,5,0,0,0,0,0,0,0,0,0],"25100268":[77199,"0025100268","02/20/1952","INO","Olympians","MIH","Hawks",0,10,0,0,0,0,0,0,0,0,0],"25100304":[77199,"0025100304","03/04/1952","INO","Olympians","FTW","Pistons",0,3,0,0,0,0,0,0,0,0,0],"25100286":[77199,"0025100286","02/27/1952","INO","Olympians","PHW","Warriors",0,13,0,0,0,0,0,0,0,0,0],"25100055":[77199,"0025100055","11/23/1951","INO","Olympians","SYR","Nationals",0,6,0,0,0,0,0,0,0,0,0]},"data":[25.0,58,null,22.8,2.8,9.0,0.313,null,null,null,1.8,2.3,0.75,null,null,4.9,2.6,null,null,null,2.4,7.4],"rank":{"PerGame":[57,53,40,null,null,null,null,57,59,34,null,null,40,36,null,null,null,55,1],"Totals":[62,58,46,null,null,null,null,62,68,34,null,null,42,40,null,null,null,63,1]},"team":"INO"},"1950":{"GameList":{"25000035":[77199,"0025000035","11/14/1950","INO","Olympians","SYR","Nationals",0,18,0,0,0,0,0,0,0,0,0],"25000030":[77199,"0025000030","11/12/1950","INO","Olympians","BOS","Celtics",0,13,0,0,0,0,0,0,0,0,0],"25000017":[77199,"0025000017","11/07/1950","INO","Olympians","NYK","Knicks",0,12,0,0,0,0,0,0,0,0,0],"25000092":[77199,"0025000092","12/03/1950","INO","Olympians","SYR","Nationals",0,7,0,0,0,0,0,0,0,0,0],"25000094":[77199,"0025000094","12/05/1950","INO","Olympians","NYK","Knicks",0,11,0,0,0,0,0,0,0,0,0],"25000095":[77199,"0025000095","12/06/1950","INO","Olympians","WAS","Capitols",0,34,0,0,0,0,0,0,0,0,0],"25000016":[77199,"0025000016","11/05/1950","INO","Olympians","FTW","Pistons",0,11,0,0,0,0,0,0,0,0,0],"25000049":[77199,"0025000049","11/18/1950","INO","Olympians","TCB","Blackhawks",0,5,0,0,0,0,0,0,0,0,0],"25000062":[77199,"0025000062","11/23/1950","INO","Olympians","SYR","Nationals",0,15,0,0,0,0,0,0,0,0,0],"25000021":[77199,"0025000021","11/09/1950","INO","Olympians","NYK","Knicks",0,13,0,0,0,0,0,0,0,0,0],"25000044":[77199,"0025000044","11/16/1950","INO","Olympians","PHW","Warriors",0,14,0,0,0,0,0,0,0,0,0],"25000068":[77199,"0025000068","11/25/1950","INO","Olympians","BAL","Bullets",0,17,0,0,0,0,0,0,0,0,0],"25000004":[77199,"0025000004","11/01/1950","INO","Olympians","WAS","Capitols",0,5,0,0,0,0,0,0,0,0,0],"25000009":[77199,"0025000009","11/04/1950","INO","Olympians","BAL","Bullets",0,14,0,0,0,0,0,0,0,0,0],"25000267":[77199,"0025000267","02/11/1951","INO","Olympians","MNL","Lakers",0,0,0,0,0,0,0,0,0,0,0],"25000088":[77199,"0025000088","12/02/1950","INO","Olympians","ROC","Royals",0,14,0,0,0,0,0,0,0,0,0],"25000078":[77199,"0025000078","11/28/1950","INO","Olympians","FTW","Pistons",0,7,0,0,0,0,0,0,0,0,0],"25000085":[77199,"0025000085","12/01/1950","INO","Olympians","MNL","Lakers",0,2,0,0,0,0,0,0,0,0,0],"25000074":[77199,"0025000074","11/26/1950","INO","Olympians","FTW","Pistons",0,16,0,0,0,0,0,0,0,0,0],"25000192":[77199,"0025000192","01/12/1951","INO","Olympians","FTW","Pistons",0,2,0,0,0,0,0,0,0,0,0],"25000056":[77199,"0025000056","11/21/1950","INO","Olympians","ROC","Royals",0,8,0,0,0,0,0,0,0,0,0],"25000051":[77199,"0025000051","11/19/1950","INO","Olympians","TCB","Blackhawks",0,9,0,0,0,0,0,0,0,0,0]},"data":[24.0,22,null,null,4.2,10.8,0.392,null,null,null,2.8,3.5,0.792,null,null,5.7,3.9,null,null,null,3.4,11.2],"rank":{"PerGame":[null,16,18,null,null,null,null,22,25,null,null,null,null,null,null,null,null,null,null],"Totals":[null,84,91,null,null,null,null,88,96,null,null,null,85,71,null,null,null,87,24]},"team":"INO"}},"headerRank":["RANK_PG_MIN","RANK_PG_FGM","RANK_PG_FGA","RANK_FG_PCT","RANK_PG_FG3M","RANK_PG_FG3A","RANK_FG3_PCT","RANK_PG_FTM","RANK_PG_FTA","RANK_FT_PCT","RANK_PG_OREB","RANK_PG_DREB","RANK_PG_REB","RANK_PG_AST","RANK_PG_STL","RANK_PG_BLK","RANK_PG_TOV","RANK_PG_PTS","RANK_PG_EFF"]}}