{"info":{"FIRST_NAME":"Darius","LAST_NAME":"Washington","WEIGHT":"","COUNTRY":"USA","SCHOOL":"Memphis","BIRTHDATE":"1985-12-06T00:00:00","HEIGHT":"","TO_YEAR":2007,"DLEAGUE":"Y","FROM_YEAR":2007,"TEAM":"","PERSON_ID":200827,"SEASON_EXP":1,"POSITION":"","ROSTERSTATUS":"Inactive","ALL_STAR":0,"PIE":0,"JERSEY":""},"career":{"header":["MIN","FGM","FGA","FG_PCT","FG3M","FG3A","FG3_PCT","FTM","FTA","FT_PCT","OREB","DREB","REB","AST","STL","BLK","TOV","PF","PTS"],"RegularSeason":{"PerGame":[8.1,1.2,2.7,0.438,0.2,0.7,0.333,0.4,0.7,0.538,0.2,0.9,1.1,0.8,0.3,0.0,0.8,0.9,2.9],"GS":0,"GP":18},"PostSeason":{}},"season":{"PostSeason":{},"headerGame":["PLAYER_ID","GAME_ID","GAME_DATE","TEAM_ABBREVIATION","TEAM_NAME","VS_TEAM_ABBREVIATION","VS_TEAM_NAME","TOV","PTS","FGM","FGA","FG3M","FG3A","PF","BLK","STL","AST","REB"],"headerData":["PLAYER_AGE","GP","GS","MIN","FGM","FGA","FG_PCT","FG3M","FG3A","FG3_PCT","FTM","FTA","FT_PCT","OREB","DREB","REB","AST","STL","BLK","TOV","PF","PTS"],"RegularSeason":{"2007":{"shotchart":{"Averages":{"header":["SHOT_ZONE_BASIC","SHOT_ZONE_AREA","SHOT_ZONE_RANGE","FGA","FGM","FG_PCT"],"row":[["Above the Break 3","Back Court(BC)","Back Court Shot",129,3,0.023],["Above the Break 3","Center(C)","24+ ft.",6849,2374,0.347],["Above the Break 3","Left Side Center(LC)","24+ ft.",12540,4481,0.357],["Above the Break 3","Right Side Center(RC)","24+ ft.",12323,4426,0.359],["Backcourt","Back Court(BC)","Back Court Shot",468,10,0.021],["In The Paint (Non-RA)","Center(C)","8-16 ft.",6435,2577,0.4],["In The Paint (Non-RA)","Center(C)","Less Than 8 ft.",15001,6210,0.414],["In The Paint (Non-RA)","Left Side(L)","8-16 ft.",2249,880,0.391],["In The Paint (Non-RA)","Right Side(R)","8-16 ft.",2226,918,0.412],["Left Corner 3","Left Side(L)","24+ ft.",6340,2479,0.391],["Mid-Range","Center(C)","16-24 ft.",8386,3433,0.409],["Mid-Range","Center(C)","8-16 ft.",1688,721,0.427],["Mid-Range","Left Side Center(LC)","16-24 ft.",10377,4195,0.404],["Mid-Range","Left Side(L)","16-24 ft.",9213,3787,0.411],["Mid-Range","Left Side(L)","8-16 ft.",8623,3268,0.379],["Mid-Range","Right Side Center(RC)","16-24 ft.",10936,4413,0.404],["Mid-Range","Right Side(R)","16-24 ft.",8205,3428,0.418],["Mid-Range","Right Side(R)","8-16 ft.",8558,3283,0.384],["Restricted Area","Center(C)","Less Than 8 ft.",64133,38456,0.6],["Right Corner 3","Right Side(R)","24+ ft.",5822,2327,0.4]]},"Details":{"header":["GAME_ID","GAME_EVENT_ID","PERIOD","MINUTES_REMAINING","SECONDS_REMAINING","EVENT_TYPE","ACTION_TYPE","SHOT_TYPE","SHOT_ZONE_BASIC","SHOT_ZONE_AREA","SHOT_ZONE_RANGE","SHOT_DISTANCE","LOC_X","LOC_Y","SHOT_ATTEMPTED_FLAG","SHOT_MADE_FLAG"],"row":[["0020700001",348,4,11,30,"Made Shot","Jump Shot","3PT Field Goal","Above the Break 3","Left Side Center(LC)","24+ ft.",25,-89,240,1,1],["0020700009",122,1,0,3,"Missed Shot","Driving Layup Shot","2PT Field Goal","Restricted Area","Center(C)","Less Than 8 ft.",0,0,0,1,0],["0020700009",330,3,2,38,"Missed Shot","Jump Shot","2PT Field Goal","Mid-Range","Right Side Center(RC)","16-24 ft.",21,153,148,1,0],["0020700009",333,3,2,10,"Made Shot","Layup Shot","2PT Field Goal","Restricted Area","Center(C)","Less Than 8 ft.",0,0,0,1,1],["0020700009",356,4,11,19,"Made Shot","Running Jump Shot","2PT Field Goal","In The Paint (Non-RA)","Center(C)","8-16 ft.",9,38,84,1,1],["0020700009",359,4,11,6,"Missed Shot","Floating Jump shot","2PT Field Goal","In The Paint (Non-RA)","Center(C)","Less Than 8 ft.",4,1,48,1,0],["0020700025",399,4,6,46,"Missed Shot","Jump Shot","2PT Field Goal","Mid-Range","Left Side(L)","8-16 ft.",10,-100,-5,1,0],["0020700025",436,4,2,36,"Missed Shot","Jump Shot","3PT Field Goal","Above the Break 3","Left Side Center(LC)","24+ ft.",24,-194,155,1,0],["0020700025",447,4,1,40,"Missed Shot","Floating Jump shot","2PT Field Goal","In The Paint (Non-RA)","Center(C)","8-16 ft.",8,-5,81,1,0],["0020700073",100,2,10,55,"Missed Shot","Jump Shot","3PT Field Goal","Above the Break 3","Right Side Center(RC)","24+ ft.",24,182,169,1,0],["0020700073",137,2,5,33,"Made Shot","Layup Shot","2PT Field Goal","Restricted Area","Center(C)","Less Than 8 ft.",0,0,0,1,1],["0020700073",299,3,1,41,"Made Shot","Reverse Layup Shot","2PT Field Goal","Restricted Area","Center(C)","Less Than 8 ft.",0,0,0,1,1],["0020700073",311,3,0,1,"Made Shot","Layup Shot","2PT Field Goal","Restricted Area","Center(C)","Less Than 8 ft.",0,0,0,1,1],["0020700090",130,2,9,44,"Made Shot","Driving Finger Roll Layup Shot","2PT Field Goal","Restricted Area","Center(C)","Less Than 8 ft.",2,6,20,1,1],["0020700090",150,2,7,27,"Made Shot","Jump Shot","3PT Field Goal","Above the Break 3","Left Side Center(LC)","24+ ft.",25,-163,192,1,1],["0020700090",340,3,0,44,"Missed Shot","Layup Shot","2PT Field Goal","Restricted Area","Center(C)","Less Than 8 ft.",2,11,26,1,0],["0020700090",385,4,8,48,"Made Shot","Reverse Layup Shot","2PT Field Goal","Restricted Area","Center(C)","Less Than 8 ft.",2,-10,18,1,1],["0020700090",405,4,5,57,"Missed Shot","Jump Shot","3PT Field Goal","Above the Break 3","Center(C)","24+ ft.",26,11,265,1,0],["0020700090",425,4,3,34,"Made Shot","Layup Shot","2PT Field Goal","Restricted Area","Center(C)","Less Than 8 ft.",1,0,13,1,1],["0020700101",324,3,0,9,"Made Shot","Jump Shot","2PT Field Goal","Mid-Range","Right Side(R)","16-24 ft.",23,192,138,1,1],["0020700101",346,4,9,49,"Made Shot","Jump Shot","3PT Field Goal","Right Corner 3","Right Side(R)","24+ ft.",22,222,48,1,1],["0020700101",458,4,0,22,"Missed Shot","Jump Shot","2PT Field Goal","Mid-Range","Right Side Center(RC)","16-24 ft.",16,118,109,1,0],["0020700117",491,4,1,17,"Made Shot","Jump Shot","2PT Field Goal","Mid-Range","Left Side Center(LC)","16-24 ft.",22,-118,189,1,1],["0020700150",444,4,0,6,"Missed Shot","Jump Shot","3PT Field Goal","Above the Break 3","Right Side Center(RC)","24+ ft.",27,159,229,1,0],["0020700176",433,4,0,59,"Missed Shot","Jump Shot","2PT Field Goal","Mid-Range","Left Side Center(LC)","16-24 ft.",17,-100,143,1,0],["0020700195",483,4,0,3,"Missed Shot","Jump Shot","2PT Field Goal","Mid-Range","Center(C)","16-24 ft.",22,-6,222,1,0],["0020700200",303,3,2,18,"Missed Shot","Jump Shot","2PT Field Goal","Mid-Range","Right Side Center(RC)","16-24 ft.",21,120,176,1,0],["0020700200",319,3,0,50,"Missed Shot","Jump Shot","2PT Field Goal","In The Paint (Non-RA)","Center(C)","Less Than 8 ft.",6,56,41,1,0],["0020700200",327,3,0,33,"Made Shot","Driving Layup Shot","2PT Field Goal","Restricted Area","Center(C)","Less Than 8 ft.",0,0,0,1,1],["0020700200",338,3,0,0,"Made Shot","Jump Shot","3PT Field Goal","Above the Break 3","Right Side Center(RC)","24+ ft.",33,136,304,1,1],["0020700200",349,4,10,40,"Missed Shot","Jump Shot","3PT Field Goal","Above the Break 3","Right Side Center(RC)","24+ ft.",24,171,171,1,0],["0020700200",373,4,7,54,"Made Shot","Layup Shot","2PT Field Goal","Restricted Area","Center(C)","Less Than 8 ft.",0,0,0,1,1],["0020700200",447,4,2,7,"Missed Shot","Jump Shot","2PT Field Goal","In The Paint (Non-RA)","Center(C)","Less Than 8 ft.",7,0,72,1,0],["0020700326",98,1,1,46,"Made Shot","Jump Shot","2PT Field Goal","Mid-Range","Left Side Center(LC)","16-24 ft.",21,-123,171,1,1],["0020700326",114,1,0,32,"Missed Shot","Jump Shot","2PT Field Goal","Mid-Range","Center(C)","16-24 ft.",22,47,217,1,0],["0020700326",143,2,9,45,"Missed Shot","Driving Dunk Shot","2PT Field Goal","Restricted Area","Center(C)","Less Than 8 ft.",0,0,0,1,0],["0020700326",254,2,1,3,"Missed Shot","Jump Shot","3PT Field Goal","Above the Break 3","Right Side Center(RC)","24+ ft.",24,107,224,1,0],["0020700348",104,1,0,54,"Made Shot","Layup Shot","2PT Field Goal","Restricted Area","Center(C)","Less Than 8 ft.",1,0,18,1,1],["0020700348",122,2,11,30,"Missed Shot","Jump Shot","2PT Field Goal","Restricted Area","Center(C)","Less Than 8 ft.",3,-15,35,1,0],["0020700348",309,3,0,46,"Missed Shot","Jump Shot","2PT Field Goal","Mid-Range","Center(C)","16-24 ft.",16,-2,163,1,0],["0020700348",351,4,7,56,"Made Shot","Jump Shot","2PT Field Goal","Mid-Range","Left Side(L)","8-16 ft.",15,-159,0,1,1],["0020700348",353,4,7,12,"Missed Shot","Floating Jump shot","2PT Field Goal","In The Paint (Non-RA)","Center(C)","8-16 ft.",8,5,81,1,0],["0020700348",420,4,0,52,"Missed Shot","Jump Shot","2PT Field Goal","Mid-Range","Right Side Center(RC)","16-24 ft.",17,138,112,1,0],["0020700372",45,1,5,21,"Made Shot","Pullup Jump shot","2PT Field Goal","Mid-Range","Right Side(R)","8-16 ft.",13,89,99,1,1],["0020700372",50,1,4,57,"Made Shot","Layup Shot","2PT Field Goal","Restricted Area","Center(C)","Less Than 8 ft.",0,0,0,1,1],["0020700372",81,1,1,41,"Missed Shot","Jump Shot","3PT Field Goal","Above the Break 3","Center(C)","24+ ft.",25,39,248,1,0],["0020700372",91,1,0,43,"Missed Shot","Jump Shot","2PT Field Goal","Mid-Range","Center(C)","16-24 ft.",21,-6,217,1,0],["0020700372",95,1,0,2,"Missed Shot","Jump Shot","3PT Field Goal","Above the Break 3","Left Side Center(LC)","24+ ft.",25,-174,183,1,0]]}},"GameList":{"20700176":[200827,"0020700176","11/23/2007","SAS","Spurs","MEM","Grizzlies",2,0,0,1,0,0,2,0,0,0,1],"20700117":[200827,"0020700117","11/15/2007","SAS","Spurs","DAL","Mavericks",0,2,1,1,0,0,0,0,0,0,1],"20700001":[200827,"0020700001","10/30/2007","SAS","Spurs","POR","Trail Blazers",1,3,1,1,1,1,1,0,1,2,1],"20700059":[200827,"0020700059","11/07/2007","SAS","Spurs","MIA","Heat",0,0,0,0,0,0,1,0,0,0,0],"20700050":[200827,"0020700050","11/06/2007","SAS","Spurs","HOU","Rockets",1,0,0,0,0,0,0,0,0,0,0],"20700090":[200827,"0020700090","11/11/2007","SAS","Spurs","MIL","Bucks",2,11,4,6,1,2,2,0,1,2,2],"20700195":[200827,"0020700195","11/25/2007","SAS","Spurs","SEA","SuperSonics",0,2,0,1,0,0,0,0,0,0,0],"20700073":[200827,"0020700073","11/09/2007","SAS","Spurs","NOH","Hornets",0,7,3,4,0,1,1,0,0,2,1],"20700126":[200827,"0020700126","11/16/2007","SAS","Spurs","HOU","Rockets",0,0,0,0,0,0,0,0,0,0,0],"20700101":[200827,"0020700101","11/13/2007","SAS","Spurs","LAL","Lakers",1,5,2,3,1,1,1,0,0,2,3],"20700348":[200827,"0020700348","12/15/2007","SAS","Spurs","DEN","Nuggets",2,4,2,6,0,0,2,0,0,1,2],"20700326":[200827,"0020700326","12/13/2007","SAS","Spurs","LAL","Lakers",0,3,1,4,0,1,0,0,1,1,1],"20700009":[200827,"0020700009","10/31/2007","SAS","Spurs","MEM","Grizzlies",2,4,2,5,0,0,3,0,1,2,1],"20700025":[200827,"0020700025","11/02/2007","SAS","Spurs","SAC","Kings",2,0,0,3,0,1,1,0,0,2,3],"20700216":[200827,"0020700216","11/28/2007","SAS","Spurs","WAS","Wizards",0,0,0,0,0,0,0,0,0,0,1],"20700372":[200827,"0020700372","12/19/2007","SAS","Spurs","MEM","Grizzlies",0,4,2,5,0,2,2,0,0,0,1],"20700150":[200827,"0020700150","11/20/2007","SAS","Spurs","ATL","Hawks",1,0,0,1,0,1,0,0,0,0,0],"20700200":[200827,"0020700200","11/26/2007","SAS","Spurs","SAC","Kings",0,8,3,7,1,2,0,0,1,1,2]},"data":[22.0,18,0,8.1,1.2,2.7,0.438,0.2,0.7,0.333,0.4,0.7,0.538,0.2,0.9,1.1,0.8,0.3,0.0,0.8,0.9,2.9],"rank":{"PerGame":[null,null,null,null,null,null,null,null,null,null,null,null,null,null,null,null,null,null,null],"Totals":[398,381,387,null,255,270,null,389,382,null,399,396,397,351,379,415,360,386,398]},"team":"SAS"}},"headerRank":["RANK_PG_MIN","RANK_PG_FGM","RANK_PG_FGA","RANK_FG_PCT","RANK_PG_FG3M","RANK_PG_FG3A","RANK_FG3_PCT","RANK_PG_FTM","RANK_PG_FTA","RANK_FT_PCT","RANK_PG_OREB","RANK_PG_DREB","RANK_PG_REB","RANK_PG_AST","RANK_PG_STL","RANK_PG_BLK","RANK_PG_TOV","RANK_PG_PTS","RANK_PG_EFF"]}}