{"info":{"FIRST_NAME":"Gerard","LAST_NAME":"King","WEIGHT":"","COUNTRY":"USA","SCHOOL":"Nicholls State","BIRTHDATE":"1972-11-25T00:00:00","HEIGHT":"","TO_YEAR":2000,"DLEAGUE":"N","FROM_YEAR":1998,"TEAM":"","PERSON_ID":1562,"SEASON_EXP":2,"POSITION":"","ROSTERSTATUS":"Inactive","ALL_STAR":0,"PIE":0,"JERSEY":""},"career":{"header":["MIN","FGM","FGA","FG_PCT","FG3M","FG3A","FG3_PCT","FTM","FTA","FT_PCT","OREB","DREB","REB","AST","STL","BLK","TOV","PF","PTS"],"RegularSeason":{"PerGame":[14.5,1.9,3.7,0.503,0.0,0.0,0.0,0.8,1.0,0.744,1.0,2.1,3.1,0.7,0.4,0.2,0.7,1.9,4.5],"GS":31,"GP":126},"PostSeason":{"PerGame":[1.8,0.3,0.5,0.5,0.0,0.0,0.0,0.0,0.0,0.0,0.0,0.5,0.5,0.1,0.0,0.1,0.1,0.3,0.5],"GS":0,"GP":8}},"season":{"PostSeason":{"1998":{"shotchart":{"Averages":{"header":["SHOT_ZONE_BASIC","SHOT_ZONE_AREA","SHOT_ZONE_RANGE","FGA","FGM","FG_PCT"],"row":[["Above the Break 3","Back Court(BC)","Back Court Shot",6,0,0.0],["Above the Break 3","Center(C)","24+ ft.",304,84,0.276],["Above the Break 3","Left Side Center(LC)","24+ ft.",512,158,0.309],["Above the Break 3","Right Side Center(RC)","24+ ft.",503,171,0.34],["Backcourt","Back Court(BC)","Back Court Shot",18,0,0.0],["In The Paint (Non-RA)","Center(C)","8-16 ft.",236,91,0.386],["In The Paint (Non-RA)","Center(C)","Less Than 8 ft.",1142,426,0.373],["In The Paint (Non-RA)","Left Side(L)","8-16 ft.",88,27,0.307],["In The Paint (Non-RA)","Right Side(R)","8-16 ft.",101,35,0.347],["Left Corner 3","Left Side(L)","24+ ft.",227,74,0.326],["Mid-Range","Center(C)","8-16 ft.",110,48,0.436],["Mid-Range","Center(C)","16-24 ft.",316,127,0.402],["Mid-Range","Left Side Center(LC)","16-24 ft.",348,128,0.368],["Mid-Range","Left Side(L)","16-24 ft.",488,184,0.377],["Mid-Range","Left Side(L)","8-16 ft.",879,328,0.373],["Mid-Range","Right Side Center(RC)","16-24 ft.",342,149,0.436],["Mid-Range","Right Side(R)","16-24 ft.",447,159,0.356],["Mid-Range","Right Side(R)","8-16 ft.",720,261,0.363],["Restricted Area","Center(C)","Less Than 8 ft.",2828,1651,0.584],["Right Corner 3","Right Side(R)","24+ ft.",242,92,0.38]]},"Details":{"header":["GAME_ID","GAME_EVENT_ID","PERIOD","MINUTES_REMAINING","SECONDS_REMAINING","EVENT_TYPE","ACTION_TYPE","SHOT_TYPE","SHOT_ZONE_BASIC","SHOT_ZONE_AREA","SHOT_ZONE_RANGE","SHOT_DISTANCE","LOC_X","LOC_Y","SHOT_ATTEMPTED_FLAG","SHOT_MADE_FLAG"],"row":[["0049800022",439,4,0,56,"Made Shot","Jump Shot","2PT Field Goal","Mid-Range","Right Side(R)","16-24 ft.",16,162,-10,1,1],["0049800022",442,4,0,24,"Missed Shot","Jump Shot","2PT Field Goal","Mid-Range","Right Side(R)","16-24 ft.",16,169,-10,1,0],["0049800078",477,4,1,48,"Missed Shot","Jump Shot","2PT Field Goal","Mid-Range","Left Side(L)","8-16 ft.",9,-98,-8,1,0],["0049800078",490,4,0,28,"Made Shot","Jump Shot","2PT Field Goal","Mid-Range","Left Side(L)","8-16 ft.",11,-113,5,1,1]]}},"GameList":{"49800085":[1562,"0049800085","06/21/1999","SAS","Spurs","NYK","Knicks",0,0,0,0,0,0,0,0,0,0,0],"49800084":[1562,"0049800084","06/18/1999","SAS","Spurs","NYK","Knicks",0,0,0,0,0,0,0,0,0,0,0],"49800078":[1562,"0049800078","06/04/1999","SAS","Spurs","POR","Trail Blazers",0,2,1,2,0,0,1,1,0,1,1],"49800079":[1562,"0049800079","06/06/1999","SAS","Spurs","POR","Trail Blazers",0,0,0,0,0,0,1,0,0,0,1],"49800031":[1562,"0049800031","05/15/1999","SAS","Spurs","MIN","Timberwolves",0,0,0,0,0,0,0,0,0,0,0],"49800054":[1562,"0049800054","05/23/1999","SAS","Spurs","LAL","Lakers",1,0,0,0,0,0,0,0,0,0,1],"49800022":[1562,"0049800022","05/13/1999","SAS","Spurs","MIN","Timberwolves",0,2,1,2,0,0,0,0,0,0,1],"49800051":[1562,"0049800051","05/22/1999","SAS","Spurs","LAL","Lakers",0,0,0,0,0,0,0,0,0,0,0]},"data":[26.0,8,0,1.8,0.3,0.5,0.5,0.0,0.0,0.0,0.0,0.0,0.0,0.0,0.5,0.5,0.1,0.0,0.1,0.1,0.3,0.5],"rank":{"PerGame":[null,null,null,null,null,null,null,null,null,null,null,null,null,null,null,null,null,null,null],"Totals":[165,148,158,null,87,112,null,156,159,null,160,137,144,142,151,76,148,157,152]},"team":"SAS"}},"headerGame":["PLAYER_ID","GAME_ID","GAME_DATE","TEAM_ABBREVIATION","TEAM_NAME","VS_TEAM_ABBREVIATION","VS_TEAM_NAME","TOV","PTS","FGM","FGA","FG3M","FG3A","PF","BLK","STL","AST","REB"],"headerData":["PLAYER_AGE","GP","GS","MIN","FGM","FGA","FG_PCT","FG3M","FG3A","FG3_PCT","FTM","FTA","FT_PCT","OREB","DREB","REB","AST","STL","BLK","TOV","PF","PTS"],"RegularSeason":{"1999":{"shotchart":{"Averages":{"header":["SHOT_ZONE_BASIC","SHOT_ZONE_AREA","SHOT_ZONE_RANGE","FGA","FGM","FG_PCT"],"row":[["Above the Break 3","Back Court(BC)","Back Court Shot",125,6,0.048],["Above the Break 3","Center(C)","24+ ft.",5382,1784,0.331],["Above the Break 3","Left Side Center(LC)","24+ ft.",9320,3273,0.351],["Above the Break 3","Right Side Center(RC)","24+ ft.",9595,3380,0.352],["Backcourt","Back Court(BC)","Back Court Shot",244,7,0.029],["In The Paint (Non-RA)","Center(C)","8-16 ft.",5074,2063,0.407],["In The Paint (Non-RA)","Center(C)","Less Than 8 ft.",20928,7588,0.363],["In The Paint (Non-RA)","Left Side(L)","8-16 ft.",1818,709,0.39],["In The Paint (Non-RA)","Right Side(R)","8-16 ft.",1839,700,0.381],["Left Corner 3","Left Side(L)","24+ ft.",3897,1509,0.387],["Mid-Range","Center(C)","16-24 ft.",6057,2561,0.423],["Mid-Range","Center(C)","8-16 ft.",2126,863,0.406],["Mid-Range","Left Side Center(LC)","16-24 ft.",8559,3511,0.41],["Mid-Range","Left Side(L)","16-24 ft.",10432,4260,0.408],["Mid-Range","Left Side(L)","8-16 ft.",15902,5949,0.374],["Mid-Range","Right Side Center(RC)","16-24 ft.",8614,3574,0.415],["Mid-Range","Right Side(R)","16-24 ft.",9445,3675,0.389],["Mid-Range","Right Side(R)","8-16 ft.",13513,5085,0.376],["Restricted Area","Center(C)","Less Than 8 ft.",58423,35587,0.609],["Right Corner 3","Right Side(R)","24+ ft.",3925,1506,0.384]]},"Details":{"header":["GAME_ID","GAME_EVENT_ID","PERIOD","MINUTES_REMAINING","SECONDS_REMAINING","EVENT_TYPE","ACTION_TYPE","SHOT_TYPE","SHOT_ZONE_BASIC","SHOT_ZONE_AREA","SHOT_ZONE_RANGE","SHOT_DISTANCE","LOC_X","LOC_Y","SHOT_ATTEMPTED_FLAG","SHOT_MADE_FLAG"],"row":[["0029900003",199,2,6,31,"Made Shot","Hook Shot","2PT Field Goal","Restricted Area","Center(C)","Less Than 8 ft.",3,-6,33,1,1],["0029900003",205,2,5,40,"Made Shot","Jump Shot","2PT Field Goal","Mid-Range","Left Side(L)","8-16 ft.",11,-111,3,1,1],["0029900003",248,2,1,12,"Made Shot","Jump Shot","2PT Field Goal","In The Paint (Non-RA)","Right Side(R)","8-16 ft.",11,74,87,1,1],["0029900003",259,2,0,30,"Made Shot","Jump Shot","2PT Field Goal","Mid-Range","Left Side(L)","16-24 ft.",16,-162,-14,1,1],["0029900003",385,4,11,9,"Missed Shot","Jump Shot","2PT Field Goal","Mid-Range","Left Side(L)","8-16 ft.",9,-89,33,1,0],["0029900003",436,4,6,35,"Made Shot","Jump Shot","2PT Field Goal","Mid-Range","Left Side(L)","8-16 ft.",11,-111,10,1,1],["0029900003",438,4,6,9,"Missed Shot","Jump Shot","2PT Field Goal","In The Paint (Non-RA)","Center(C)","Less Than 8 ft.",4,35,33,1,0],["0029900014",184,2,7,43,"Made Shot","Layup Shot","2PT Field Goal","Restricted Area","Center(C)","Less Than 8 ft.",2,23,0,1,1],["0029900014",242,2,2,29,"Made Shot","Slam Dunk Shot","2PT Field Goal","Restricted Area","Center(C)","Less Than 8 ft.",3,31,-3,1,1],["0029900014",328,3,6,12,"Missed Shot","Jump Shot","2PT Field Goal","Mid-Range","Right Side(R)","8-16 ft.",14,147,8,1,0],["0029900036",193,2,6,21,"Made Shot","Jump Shot","2PT Field Goal","Mid-Range","Right Side(R)","8-16 ft.",14,149,0,1,1],["0029900036",206,2,4,46,"Missed Shot","Jump Shot","2PT Field Goal","Mid-Range","Right Side(R)","8-16 ft.",11,93,61,1,0],["0029900046",386,3,0,5,"Missed Shot","Jump Shot","2PT Field Goal","Mid-Range","Right Side Center(RC)","16-24 ft.",19,123,156,1,0],["0029900046",415,4,9,45,"Missed Shot","Hook Shot","2PT Field Goal","In The Paint (Non-RA)","Center(C)","Less Than 8 ft.",4,12,42,1,0],["0029900046",427,4,9,14,"Missed Shot","Jump Shot","2PT Field Goal","Mid-Range","Left Side(L)","8-16 ft.",14,-149,5,1,0],["0029900046",524,4,1,7,"Made Shot","Layup Shot","2PT Field Goal","Restricted Area","Center(C)","Less Than 8 ft.",0,0,0,1,1],["0029900075",155,2,9,25,"Made Shot","Layup Shot","2PT Field Goal","In The Paint (Non-RA)","Center(C)","Less Than 8 ft.",4,40,10,1,1],["0029900075",191,2,6,31,"Made Shot","Dunk Shot","2PT Field Goal","Restricted Area","Center(C)","Less Than 8 ft.",2,18,21,1,1],["0029900075",198,2,5,18,"Made Shot","Jump Shot","2PT Field Goal","Mid-Range","Right Side(R)","8-16 ft.",11,115,-5,1,1],["0029900075",304,3,6,22,"Missed Shot","Jump Shot","2PT Field Goal","Mid-Range","Left Side(L)","8-16 ft.",14,-147,3,1,0],["0029900075",320,3,4,45,"Missed Shot","Jump Shot","2PT Field Goal","In The Paint (Non-RA)","Center(C)","Less Than 8 ft.",4,27,33,1,0],["0029900075",324,3,4,23,"Made Shot","Hook Shot","2PT Field Goal","In The Paint (Non-RA)","Center(C)","Less Than 8 ft.",5,48,27,1,1],["0029900075",354,3,1,20,"Missed Shot","Jump Shot","2PT Field Goal","Restricted Area","Center(C)","Less Than 8 ft.",3,-1,33,1,0],["0029900084",125,1,1,2,"Missed Shot","Jump Shot","2PT Field Goal","Mid-Range","Left Side(L)","8-16 ft.",10,-109,-1,1,0],["0029900084",132,1,0,0,"Missed Shot","Tip Shot","2PT Field Goal","Restricted Area","Center(C)","Less Than 8 ft.",3,1,31,1,0],["0029900084",139,2,11,45,"Missed Shot","Jump Shot","2PT Field Goal","In The Paint (Non-RA)","Center(C)","Less Than 8 ft.",4,-42,10,1,0],["0029900084",145,2,11,9,"Made Shot","Layup Shot","2PT Field Goal","Restricted Area","Center(C)","Less Than 8 ft.",0,-6,3,1,1],["0029900084",158,2,9,52,"Made Shot","Jump Shot","2PT Field Goal","Mid-Range","Right Side Center(RC)","16-24 ft.",17,117,130,1,1],["0029900084",173,2,8,12,"Made Shot","Layup Shot","2PT Field Goal","Restricted Area","Center(C)","Less Than 8 ft.",2,14,16,1,1],["0029900084",175,2,7,37,"Made Shot","Layup Shot","2PT Field Goal","Restricted Area","Center(C)","Less Than 8 ft.",1,14,3,1,1],["0029900084",177,2,6,57,"Missed Shot","Jump Shot","2PT Field Goal","In The Paint (Non-RA)","Center(C)","Less Than 8 ft.",5,-42,42,1,0],["0029900084",319,3,6,10,"Made Shot","Jump Shot","2PT Field Goal","In The Paint (Non-RA)","Center(C)","Less Than 8 ft.",5,-51,-1,1,1],["0029900084",343,3,3,13,"Missed Shot","Jump Shot","2PT Field Goal","Mid-Range","Left Side(L)","8-16 ft.",15,-158,-1,1,0],["0029900084",355,3,1,59,"Made Shot","Layup Shot","2PT Field Goal","Restricted Area","Center(C)","Less Than 8 ft.",1,8,10,1,1],["0029900084",377,4,11,32,"Made Shot","Jump Shot","2PT Field Goal","Mid-Range","Right Side(R)","8-16 ft.",13,138,21,1,1],["0029900084",430,4,6,41,"Missed Shot","Jump Shot","2PT Field Goal","In The Paint (Non-RA)","Right Side(R)","8-16 ft.",8,72,48,1,0],["0029900084",439,4,5,53,"Made Shot","Layup Shot","2PT Field Goal","Restricted Area","Center(C)","Less Than 8 ft.",1,14,3,1,1],["0029900084",456,4,3,34,"Made Shot","Jump Shot","2PT Field Goal","Mid-Range","Left Side Center(LC)","16-24 ft.",16,-72,147,1,1],["0029900100",80,1,4,37,"Missed Shot","Jump Shot","2PT Field Goal","In The Paint (Non-RA)","Center(C)","Less Than 8 ft.",5,-51,-5,1,0],["0029900100",395,3,0,39,"Missed Shot","Jump Shot","2PT Field Goal","Mid-Range","Right Side(R)","16-24 ft.",18,186,-33,1,0],["0029900100",417,4,10,42,"Missed Shot","Jump Shot","2PT Field Goal","In The Paint (Non-RA)","Center(C)","Less Than 8 ft.",5,18,57,1,0],["0029900119",101,1,1,56,"Made Shot","Jump Shot","2PT Field Goal","Mid-Range","Right Side(R)","8-16 ft.",10,93,51,1,1],["0029900119",141,2,9,23,"Made Shot","Jump Shot","2PT Field Goal","In The Paint (Non-RA)","Right Side(R)","8-16 ft.",10,70,78,1,1],["0029900119",332,3,4,42,"Missed Shot","Jump Shot","2PT Field Goal","In The Paint (Non-RA)","Center(C)","Less Than 8 ft.",4,5,46,1,0],["0029900119",410,4,9,8,"Missed Shot","Jump Shot","2PT Field Goal","Mid-Range","Right Side(R)","8-16 ft.",11,115,0,1,0],["0029900135",82,1,2,51,"Made Shot","Layup Shot","2PT Field Goal","Restricted Area","Center(C)","Less Than 8 ft.",0,5,0,1,1],["0029900135",384,4,7,45,"Missed Shot","Jump Shot","2PT Field Goal","In The Paint (Non-RA)","Center(C)","Less Than 8 ft.",7,-74,3,1,0],["0029900153",115,2,11,33,"Made Shot","Driving Layup Shot","2PT Field Goal","Restricted Area","Center(C)","Less Than 8 ft.",1,12,3,1,1],["0029900153",128,2,10,14,"Missed Shot","Jump Shot","2PT Field Goal","Mid-Range","Left Side(L)","16-24 ft.",17,-169,-33,1,0],["0029900153",148,2,8,42,"Made Shot","Tip Shot","2PT Field Goal","Restricted Area","Center(C)","Less Than 8 ft.",0,-1,3,1,1],["0029900153",255,2,0,0,"Missed Shot","Layup Shot","2PT Field Goal","Restricted Area","Center(C)","Less Than 8 ft.",1,-14,3,1,0],["0029900161",357,3,3,45,"Made Shot","Dunk Shot","2PT Field Goal","Restricted Area","Center(C)","Less Than 8 ft.",0,0,0,1,1],["0029900161",476,4,4,38,"Missed Shot","Jump Shot","2PT Field Goal","Mid-Range","Right Side(R)","8-16 ft.",9,89,25,1,0],["0029900173",423,4,5,43,"Made Shot","Jump Shot","2PT Field Goal","In The Paint (Non-RA)","Center(C)","Less Than 8 ft.",7,72,33,1,1],["0029900173",450,4,3,48,"Made Shot","Layup Shot","2PT Field Goal","Restricted Area","Center(C)","Less Than 8 ft.",0,0,0,1,1],["0029900201",90,1,2,11,"Made Shot","Layup Shot","2PT Field Goal","Restricted Area","Center(C)","Less Than 8 ft.",0,0,0,1,1],["0029900234",383,3,3,55,"Made Shot","Jump Shot","2PT Field Goal","Mid-Range","Right Side Center(RC)","16-24 ft.",17,128,119,1,1],["0029900234",394,3,2,25,"Made Shot","Layup Shot","2PT Field Goal","Restricted Area","Center(C)","Less Than 8 ft.",1,18,3,1,1],["0029900234",408,3,1,13,"Missed Shot","Jump Shot","2PT Field Goal","Mid-Range","Left Side(L)","16-24 ft.",16,-160,46,1,0],["0029900234",465,4,8,8,"Made Shot","Layup Shot","2PT Field Goal","Restricted Area","Center(C)","Less Than 8 ft.",0,5,3,1,1],["0029900234",535,4,1,51,"Made Shot","Jump Shot","2PT Field Goal","In The Paint (Non-RA)","Center(C)","Less Than 8 ft.",5,55,10,1,1],["0029900234",545,4,0,53,"Missed Shot","Layup Shot","2PT Field Goal","Restricted Area","Center(C)","Less Than 8 ft.",2,18,10,1,0],["0029900250",118,1,0,9,"Made Shot","Jump Shot","2PT Field Goal","In The Paint (Non-RA)","Right Side(R)","8-16 ft.",8,55,68,1,1],["0029900258",218,2,2,41,"Made Shot","Jump Shot","2PT Field Goal","Mid-Range","Center(C)","16-24 ft.",18,-25,179,1,1],["0029900258",509,4,0,43,"Made Shot","Layup Shot","2PT Field Goal","Restricted Area","Center(C)","Less Than 8 ft.",0,0,0,1,1],["0029900270",151,2,6,45,"Made Shot","Layup Shot","2PT Field Goal","Restricted Area","Center(C)","Less Than 8 ft.",0,0,0,1,1],["0029900270",154,2,6,15,"Missed Shot","Jump Shot","2PT Field Goal","Mid-Range","Right Side Center(RC)","16-24 ft.",17,72,154,1,0],["0029900270",171,2,4,19,"Made Shot","Layup Shot","2PT Field Goal","Restricted Area","Center(C)","Less Than 8 ft.",0,0,0,1,1],["0029900270",320,3,0,6,"Made Shot","Jump Shot","2PT Field Goal","Mid-Range","Right Side(R)","8-16 ft.",13,117,63,1,1],["0029900270",329,4,10,58,"Missed Shot","Jump Shot","2PT Field Goal","In The Paint (Non-RA)","Center(C)","8-16 ft.",8,-6,81,1,0],["0029900270",434,4,1,52,"Made Shot","Jump Shot","2PT Field Goal","In The Paint (Non-RA)","Center(C)","Less Than 8 ft.",5,-51,12,1,1],["0029900290",143,2,9,19,"Missed Shot","Layup Shot","2PT Field Goal","Restricted Area","Center(C)","Less Than 8 ft.",1,18,-8,1,0],["0029900357",401,4,10,57,"Made Shot","Layup Shot","2PT Field Goal","Restricted Area","Center(C)","Less Than 8 ft.",0,0,0,1,1],["0029900406",268,2,0,0,"Missed Shot","Tip Shot","2PT Field Goal","Restricted Area","Center(C)","Less Than 8 ft.",1,12,5,1,0],["0029900413",214,2,1,18,"Missed Shot","Jump Shot","2PT Field Goal","Mid-Range","Right Side(R)","8-16 ft.",14,149,-16,1,0],["0029900426",463,4,0,30,"Missed Shot","Jump Shot","2PT Field Goal","Mid-Range","Left Side Center(LC)","16-24 ft.",16,-74,149,1,0],["0029900444",100,1,1,49,"Made Shot","Tip Shot","2PT Field Goal","Restricted Area","Center(C)","Less Than 8 ft.",0,0,0,1,1],["0029900444",162,2,6,52,"Missed Shot","Tip Shot","2PT Field Goal","Restricted Area","Center(C)","Less Than 8 ft.",0,0,0,1,0],["0029900444",324,3,4,6,"Missed Shot","Layup Shot","2PT Field Goal","Restricted Area","Center(C)","Less Than 8 ft.",0,0,0,1,0],["0029900444",357,3,0,59,"Missed Shot","Tip Shot","2PT Field Goal","Restricted Area","Center(C)","Less Than 8 ft.",0,0,0,1,0],["0029900444",381,4,11,10,"Made Shot","Layup Shot","2PT Field Goal","Restricted Area","Center(C)","Less Than 8 ft.",0,0,0,1,1],["0029900457",116,2,11,37,"Made Shot","Jump Shot","2PT Field Goal","Mid-Range","Left Side(L)","8-16 ft.",12,-117,-29,1,1],["0029900457",156,2,7,29,"Made Shot","Jump Shot","2PT Field Goal","Mid-Range","Right Side(R)","8-16 ft.",15,158,-23,1,1],["0029900457",183,2,4,31,"Made Shot","Jump Shot","2PT Field Goal","Mid-Range","Left Side(L)","8-16 ft.",14,-132,57,1,1],["0029900457",194,2,3,2,"Missed Shot","Jump Shot","2PT Field Goal","Restricted Area","Center(C)","Less Than 8 ft.",3,5,33,1,0],["0029900466",176,2,7,22,"Missed Shot","Jump Shot","2PT Field Goal","Mid-Range","Left Side(L)","8-16 ft.",15,-83,126,1,0],["0029900486",521,4,0,31,"Missed Shot","Jump Shot","2PT Field Goal","Restricted Area","Center(C)","Less Than 8 ft.",3,33,3,1,0],["0029900495",479,4,1,43,"Missed Shot","Jump Shot","2PT Field Goal","In The Paint (Non-RA)","Center(C)","Less Than 8 ft.",6,-12,63,1,0],["0029900584",27,1,7,59,"Made Shot","Layup Shot","2PT Field Goal","Restricted Area","Center(C)","Less Than 8 ft.",1,10,-10,1,1],["0029900584",136,2,7,3,"Made Shot","Layup Shot","2PT Field Goal","Restricted Area","Center(C)","Less Than 8 ft.",1,-12,-3,1,1],["0029900584",186,2,1,6,"Missed Shot","Jump Shot","2PT Field Goal","Mid-Range","Right Side Center(RC)","16-24 ft.",19,83,173,1,0],["0029900584",234,3,6,36,"Made Shot","Jump Shot","2PT Field Goal","Mid-Range","Left Side(L)","8-16 ft.",14,-85,115,1,1],["0029900584",276,3,2,20,"Made Shot","Jump Shot","2PT Field Goal","In The Paint (Non-RA)","Center(C)","8-16 ft.",13,-12,134,1,1],["0029900584",411,4,0,21,"Missed Shot","Jump Shot","2PT Field Goal","Mid-Range","Left Side(L)","8-16 ft.",15,-158,-10,1,0],["0029900790",13,1,10,27,"Made Shot","Jump Shot","2PT Field Goal","Mid-Range","Left Side(L)","8-16 ft.",10,-98,-27,1,1],["0029900790",23,1,9,49,"Missed Shot","Layup Shot","2PT Field Goal","Restricted Area","Center(C)","Less Than 8 ft.",1,1,-10,1,0],["0029900790",55,1,7,3,"Missed Shot","Jump Shot","2PT Field Goal","Mid-Range","Left Side(L)","8-16 ft.",12,-128,-10,1,0],["0029900790",266,3,9,58,"Missed Shot","Jump Shot","2PT Field Goal","In The Paint (Non-RA)","Center(C)","Less Than 8 ft.",4,-40,1,1,0],["0029900818",28,1,8,40,"Made Shot","Jump Shot","2PT Field Goal","Mid-Range","Left Side(L)","8-16 ft.",12,-121,23,1,1],["0029900818",75,1,2,42,"Made Shot","Jump Shot","2PT Field Goal","In The Paint (Non-RA)","Left Side(L)","8-16 ft.",12,-70,98,1,1],["0029900818",80,1,2,2,"Made Shot","Jump Shot","2PT Field Goal","In The Paint (Non-RA)","Center(C)","Less Than 8 ft.",7,-55,57,1,1],["0029900818",107,1,0,9,"Made Shot","Layup Shot","2PT Field Goal","Restricted Area","Center(C)","Less Than 8 ft.",0,0,0,1,1],["0029900818",252,3,9,30,"Made Shot","Layup Shot","2PT Field Goal","Restricted Area","Center(C)","Less Than 8 ft.",0,0,0,1,1],["0029900818",266,3,7,8,"Made Shot","Jump Shot","2PT Field Goal","Mid-Range","Right Side(R)","8-16 ft.",13,134,1,1,1],["0029900818",277,3,5,35,"Missed Shot","Layup Shot","2PT Field Goal","Restricted Area","Center(C)","Less Than 8 ft.",0,0,0,1,0],["0029900818",375,4,6,21,"Made Shot","Layup Shot","2PT Field Goal","Restricted Area","Center(C)","Less Than 8 ft.",0,0,0,1,1],["0029900818",436,4,0,30,"Made Shot","Layup Shot","2PT Field Goal","Restricted Area","Center(C)","Less Than 8 ft.",0,0,0,1,1],["0029900823",15,1,10,9,"Missed Shot","Jump Shot","2PT Field Goal","In The Paint (Non-RA)","Center(C)","Less Than 8 ft.",4,-18,40,1,0],["0029900823",17,1,10,6,"Missed Shot","Jump Shot","2PT Field Goal","Restricted Area","Center(C)","Less Than 8 ft.",3,-33,12,1,0],["0029900823",25,1,9,35,"Made Shot","Jump Shot","2PT Field Goal","Mid-Range","Right Side(R)","8-16 ft.",14,149,-16,1,1],["0029900823",35,1,8,19,"Missed Shot","Jump Shot","2PT Field Goal","Mid-Range","Left Side(L)","8-16 ft.",15,-85,128,1,0],["0029900823",83,1,2,34,"Missed Shot","Jump Shot","2PT Field Goal","Mid-Range","Left Side(L)","8-16 ft.",13,-91,104,1,0],["0029900823",235,3,11,39,"Made Shot","Jump Shot","2PT Field Goal","In The Paint (Non-RA)","Left Side(L)","8-16 ft.",8,-55,70,1,1],["0029900823",246,3,10,5,"Made Shot","Jump Shot","2PT Field Goal","Mid-Range","Right Side(R)","16-24 ft.",17,171,-16,1,1],["0029900823",425,4,3,51,"Missed Shot","Jump Shot","2PT Field Goal","Mid-Range","Left Side(L)","8-16 ft.",14,-149,-16,1,0],["0029900823",454,4,0,43,"Missed Shot","Jump Shot","2PT Field Goal","Restricted Area","Center(C)","Less Than 8 ft.",3,25,23,1,0],["0029900837",13,1,9,41,"Missed Shot","Jump Shot","2PT Field Goal","In The Paint (Non-RA)","Center(C)","Less Than 8 ft.",6,-61,18,1,0],["0029900837",38,1,7,19,"Made Shot","Layup Shot","2PT Field Goal","Restricted Area","Center(C)","Less Than 8 ft.",3,-33,5,1,1],["0029900837",349,4,11,25,"Made Shot","Jump Shot","2PT Field Goal","Mid-Range","Center(C)","8-16 ft.",14,16,145,1,1],["0029900837",353,4,10,43,"Made Shot","Jump Shot","2PT Field Goal","Mid-Range","Left Side(L)","8-16 ft.",15,-128,93,1,1],["0029900837",368,4,8,25,"Missed Shot","Jump Shot","2PT Field Goal","Mid-Range","Left Side(L)","8-16 ft.",13,-91,93,1,0],["0029900837",399,4,5,53,"Missed Shot","Jump Shot","2PT Field Goal","Restricted Area","Center(C)","Less Than 8 ft.",3,16,33,1,0],["0029900837",413,4,4,47,"Made Shot","Jump Shot","2PT Field Goal","Mid-Range","Left Side(L)","8-16 ft.",15,-121,104,1,1],["0029900837",433,4,2,14,"Made Shot","Jump Shot","2PT Field Goal","In The Paint (Non-RA)","Center(C)","8-16 ft.",12,55,115,1,1],["0029900852",49,1,6,29,"Missed Shot","Jump Shot","2PT Field Goal","Mid-Range","Right Side(R)","8-16 ft.",14,143,18,1,0],["0029900852",55,1,5,56,"Made Shot","Hook Shot","2PT Field Goal","In The Paint (Non-RA)","Left Side(L)","8-16 ft.",9,-61,76,1,1],["0029900852",289,3,5,45,"Missed Shot","Jump Shot","2PT Field Goal","Mid-Range","Left Side(L)","16-24 ft.",16,-166,-10,1,0],["0029900862",26,1,9,9,"Made Shot","Jump Shot","2PT Field Goal","Mid-Range","Right Side Center(RC)","16-24 ft.",17,121,121,1,1],["0029900862",72,1,2,16,"Made Shot","Jump Shot","2PT Field Goal","Mid-Range","Center(C)","16-24 ft.",16,-51,162,1,1],["0029900862",150,2,6,10,"Missed Shot","Jump Shot","2PT Field Goal","Mid-Range","Left Side(L)","16-24 ft.",17,-169,-27,1,0],["0029900862",231,3,9,45,"Made Shot","Layup Shot","2PT Field Goal","Restricted Area","Center(C)","Less Than 8 ft.",0,0,0,1,1],["0029900862",236,3,8,47,"Missed Shot","Jump Shot","2PT Field Goal","Mid-Range","Left Side(L)","16-24 ft.",16,-160,-10,1,0],["0029900862",259,3,6,40,"Missed Shot","Jump Shot","2PT Field Goal","Mid-Range","Left Side(L)","8-16 ft.",14,-126,72,1,0],["0029900881",20,1,9,21,"Made Shot","Layup Shot","2PT Field Goal","Restricted Area","Center(C)","Less Than 8 ft.",1,10,-10,1,1],["0029900881",26,1,8,31,"Missed Shot","Jump Shot","2PT Field Goal","Mid-Range","Right Side Center(RC)","16-24 ft.",17,76,158,1,0],["0029900881",47,1,6,24,"Made Shot","Jump Shot","2PT Field Goal","Mid-Range","Left Side(L)","8-16 ft.",15,-158,-16,1,1],["0029900881",60,1,5,7,"Missed Shot","Layup Shot","2PT Field Goal","Restricted Area","Center(C)","Less Than 8 ft.",2,-18,12,1,0],["0029900881",112,1,0,48,"Made Shot","Layup Shot","2PT Field Goal","Restricted Area","Center(C)","Less Than 8 ft.",1,-3,-16,1,1],["0029900881",117,1,0,3,"Made Shot","Jump Shot","2PT Field Goal","In The Paint (Non-RA)","Right Side(R)","8-16 ft.",13,70,111,1,1],["0029900881",188,2,4,27,"Missed Shot","Jump Shot","2PT Field Goal","In The Paint (Non-RA)","Center(C)","8-16 ft.",13,1,134,1,0],["0029900881",194,2,3,52,"Missed Shot","Layup Shot","2PT Field Goal","Restricted Area","Center(C)","Less Than 8 ft.",1,16,1,1,0],["0029900881",259,3,8,7,"Missed Shot","Jump Shot","2PT Field Goal","In The Paint (Non-RA)","Center(C)","8-16 ft.",11,10,111,1,0],["0029900881",286,3,4,51,"Made Shot","Layup Shot","2PT Field Goal","Restricted Area","Center(C)","Less Than 8 ft.",2,1,29,1,1],["0029900881",393,4,5,16,"Missed Shot","Jump Shot","2PT Field Goal","In The Paint (Non-RA)","Center(C)","Less Than 8 ft.",4,10,40,1,0],["0029900881",490,5,0,9,"Missed Shot","Layup Shot","2PT Field Goal","Restricted Area","Center(C)","Less Than 8 ft.",2,-18,-16,1,0],["0029900898",3,1,11,16,"Missed Shot","Jump Shot","2PT Field Goal","Mid-Range","Right Side(R)","16-24 ft.",18,186,-23,1,0],["0029900898",44,1,6,27,"Missed Shot","Jump Shot","2PT Field Goal","Mid-Range","Right Side(R)","16-24 ft.",16,134,93,1,0],["0029900898",70,1,3,31,"Missed Shot","Jump Shot","2PT Field Goal","Mid-Range","Right Side(R)","8-16 ft.",15,134,76,1,0],["0029900898",106,2,11,39,"Missed Shot","Jump Shot","2PT Field Goal","Mid-Range","Left Side(L)","8-16 ft.",10,-91,53,1,0],["0029900898",224,2,0,28,"Missed Shot","Jump Shot","2PT Field Goal","Mid-Range","Left Side(L)","8-16 ft.",14,-143,29,1,0],["0029900898",280,3,5,7,"Made Shot","Jump Shot","2PT Field Goal","Mid-Range","Center(C)","8-16 ft.",14,-12,141,1,1],["0029900898",294,3,3,51,"Made Shot","Layup Shot","2PT Field Goal","Restricted Area","Center(C)","Less Than 8 ft.",0,-3,-3,1,1],["0029900898",318,3,0,41,"Missed Shot","Layup Shot","2PT Field Goal","Restricted Area","Center(C)","Less Than 8 ft.",1,-12,12,1,0],["0029900898",370,4,6,44,"Missed Shot","Jump Shot","2PT Field Goal","Restricted Area","Center(C)","Less Than 8 ft.",3,-18,33,1,0],["0029900898",394,4,3,48,"Made Shot","Jump Shot","2PT Field Goal","Mid-Range","Center(C)","16-24 ft.",17,31,169,1,1],["0029900909",34,1,8,12,"Made Shot","Jump Shot","2PT Field Goal","Mid-Range","Right Side(R)","8-16 ft.",15,134,85,1,1],["0029900909",69,1,3,52,"Missed Shot","Jump Shot","2PT Field Goal","In The Paint (Non-RA)","Center(C)","Less Than 8 ft.",6,-8,63,1,0],["0029900909",83,1,2,24,"Missed Shot","Jump Shot","2PT Field Goal","In The Paint (Non-RA)","Left Side(L)","8-16 ft.",12,-79,91,1,0],["0029900909",87,1,1,55,"Missed Shot","Jump Shot","2PT Field Goal","Mid-Range","Left Side(L)","16-24 ft.",16,-164,-5,1,0],["0029900909",256,3,9,13,"Made Shot","Jump Shot","2PT Field Goal","Mid-Range","Right Side Center(RC)","16-24 ft.",16,111,119,1,1],["0029900909",337,3,1,45,"Missed Shot","Jump Shot","2PT Field Goal","Mid-Range","Right Side Center(RC)","16-24 ft.",16,98,136,1,0],["0029900909",348,3,0,57,"Missed Shot","Jump Shot","2PT Field Goal","Mid-Range","Left Side(L)","8-16 ft.",11,-115,-5,1,0],["0029900909",360,3,0,12,"Missed Shot","Jump Shot","2PT Field Goal","Mid-Range","Left Side Center(LC)","16-24 ft.",19,-79,179,1,0],["0029900909",477,4,1,15,"Made Shot","Dunk Shot","2PT Field Goal","Restricted Area","Center(C)","Less Than 8 ft.",0,0,0,1,1],["0029900909",483,4,0,2,"Made Shot","Layup Shot","2PT Field Goal","Restricted Area","Center(C)","Less Than 8 ft.",0,0,0,1,1],["0029900923",32,1,8,4,"Missed Shot","Jump Shot","2PT Field Goal","Mid-Range","Right Side(R)","8-16 ft.",14,91,111,1,0],["0029900923",64,1,5,6,"Made Shot","Layup Shot","2PT Field Goal","Restricted Area","Center(C)","Less Than 8 ft.",0,1,-3,1,1],["0029900923",71,1,4,38,"Made Shot","Layup Shot","2PT Field Goal","Restricted Area","Center(C)","Less Than 8 ft.",1,10,1,1,1],["0029900923",74,1,4,7,"Made Shot","Jump Shot","2PT Field Goal","In The Paint (Non-RA)","Right Side(R)","8-16 ft.",14,76,121,1,1],["0029900923",91,1,2,35,"Missed Shot","Jump Shot","2PT Field Goal","Mid-Range","Left Side(L)","16-24 ft.",17,-158,76,1,0],["0029900923",269,3,10,17,"Made Shot","Jump Shot","2PT Field Goal","Mid-Range","Left Side(L)","8-16 ft.",9,-98,18,1,1],["0029900923",271,3,9,33,"Made Shot","Jump Shot","2PT Field Goal","Mid-Range","Right Side(R)","8-16 ft.",15,149,23,1,1],["0029900923",296,3,7,14,"Missed Shot","Jump Shot","2PT Field Goal","Mid-Range","Left Side Center(LC)","16-24 ft.",18,-91,162,1,0],["0029900940",30,1,9,12,"Made Shot","Layup Shot","2PT Field Goal","Restricted Area","Center(C)","Less Than 8 ft.",2,-18,-10,1,1],["0029900940",36,1,8,6,"Made Shot","Layup Shot","2PT Field Goal","Restricted Area","Center(C)","Less Than 8 ft.",2,1,-23,1,1],["0029900940",77,1,3,19,"Made Shot","Layup Shot","2PT Field Goal","Restricted Area","Center(C)","Less Than 8 ft.",0,1,5,1,1],["0029900940",89,1,2,21,"Made Shot","Jump Shot","2PT Field Goal","Mid-Range","Right Side Center(RC)","16-24 ft.",17,70,162,1,1],["0029900940",91,1,1,46,"Missed Shot","Jump Shot","2PT Field Goal","Mid-Range","Left Side(L)","16-24 ft.",17,-158,63,1,0],["0029900940",100,1,0,28,"Missed Shot","Jump Shot","2PT Field Goal","Mid-Range","Left Side(L)","8-16 ft.",11,-98,57,1,0],["0029900940",162,2,7,14,"Missed Shot","Jump Shot","2PT Field Goal","Mid-Range","Left Side(L)","16-24 ft.",16,-166,-3,1,0],["0029900940",166,2,7,5,"Made Shot","Slam Dunk Shot","2PT Field Goal","Restricted Area","Center(C)","Less Than 8 ft.",1,1,-16,1,1],["0029900940",444,4,1,5,"Missed Shot","Jump Shot","2PT Field Goal","Mid-Range","Left Side(L)","8-16 ft.",9,-91,-16,1,0],["0029900960",4,1,11,13,"Missed Shot","Jump Shot","2PT Field Goal","Mid-Range","Left Side(L)","8-16 ft.",14,-141,16,1,0],["0029900960",64,1,4,12,"Missed Shot","Jump Shot","2PT Field Goal","In The Paint (Non-RA)","Center(C)","Less Than 8 ft.",4,16,46,1,0],["0029900960",78,1,2,50,"Missed Shot","Jump Shot","2PT Field Goal","In The Paint (Non-RA)","Center(C)","Less Than 8 ft.",7,-53,46,1,0],["0029900960",261,3,8,13,"Missed Shot","Layup Shot","2PT Field Goal","Restricted Area","Center(C)","Less Than 8 ft.",0,0,0,1,0],["0029900967",25,1,9,14,"Missed Shot","Jump Shot","2PT Field Goal","Mid-Range","Left Side Center(LC)","16-24 ft.",18,-134,134,1,0],["0029900967",41,1,7,11,"Missed Shot","Jump Shot","2PT Field Goal","In The Paint (Non-RA)","Center(C)","Less Than 8 ft.",6,-40,48,1,0],["0029900967",251,3,10,54,"Made Shot","Jump Shot","2PT Field Goal","Mid-Range","Center(C)","8-16 ft.",15,40,145,1,1],["0029900967",273,3,8,52,"Missed Shot","Jump Shot","2PT Field Goal","Restricted Area","Center(C)","Less Than 8 ft.",2,-3,25,1,0],["0029900967",355,3,2,12,"Missed Shot","Jump Shot","2PT Field Goal","Mid-Range","Right Side(R)","8-16 ft.",14,89,115,1,0],["0029900967",368,3,0,13,"Missed Shot","Jump Shot","2PT Field Goal","Mid-Range","Right Side(R)","16-24 ft.",17,147,93,1,0],["0029900982",3,1,11,39,"Missed Shot","Hook Shot","2PT Field Goal","Mid-Range","Right Side(R)","8-16 ft.",11,113,-8,1,0],["0029900982",16,1,10,7,"Missed Shot","Jump Shot","2PT Field Goal","Mid-Range","Right Side(R)","16-24 ft.",17,179,-18,1,0],["0029900982",23,1,9,0,"Missed Shot","Jump Shot","2PT Field Goal","Mid-Range","Left Side(L)","16-24 ft.",18,-188,-8,1,0],["0029900982",64,1,5,7,"Made Shot","Jump Shot","2PT Field Goal","Mid-Range","Center(C)","16-24 ft.",17,10,171,1,1],["0029900982",306,3,11,10,"Made Shot","Jump Shot","2PT Field Goal","Mid-Range","Left Side(L)","8-16 ft.",15,-85,130,1,1],["0029900995",9,1,10,31,"Missed Shot","Jump Shot","2PT Field Goal","In The Paint (Non-RA)","Center(C)","Less Than 8 ft.",7,-68,27,1,0],["0029900995",19,1,8,40,"Made Shot","Layup Shot","2PT Field Goal","Restricted Area","Center(C)","Less Than 8 ft.",2,-23,8,1,1],["0029900995",35,1,6,1,"Missed Shot","Jump Shot","2PT Field Goal","In The Paint (Non-RA)","Right Side(R)","8-16 ft.",15,78,130,1,0],["0029900995",40,1,5,3,"Missed Shot","Jump Shot","2PT Field Goal","Mid-Range","Left Side(L)","8-16 ft.",12,-81,100,1,0],["0029900995",238,3,10,30,"Made Shot","Slam Dunk Shot","2PT Field Goal","Restricted Area","Center(C)","Less Than 8 ft.",0,0,0,1,1],["0029900995",240,3,9,44,"Missed Shot","Jump Shot","2PT Field Goal","Mid-Range","Left Side(L)","8-16 ft.",10,-104,8,1,0],["0029901020",8,1,10,33,"Missed Shot","Jump Shot","2PT Field Goal","Mid-Range","Right Side(R)","8-16 ft.",15,119,104,1,0],["0029901020",27,1,8,46,"Missed Shot","Jump Shot","2PT Field Goal","Mid-Range","Center(C)","16-24 ft.",16,1,162,1,0],["0029901020",57,1,6,11,"Made Shot","Jump Shot","2PT Field Goal","Mid-Range","Right Side(R)","16-24 ft.",17,171,23,1,1],["0029901020",82,1,2,54,"Made Shot","Jump Shot","2PT Field Goal","Mid-Range","Right Side(R)","16-24 ft.",17,171,33,1,1],["0029901020",103,1,0,32,"Missed Shot","Layup Shot","2PT Field Goal","Restricted Area","Center(C)","Less Than 8 ft.",0,-3,-3,1,0],["0029901033",20,1,9,43,"Made Shot","Jump Shot","2PT Field Goal","Mid-Range","Right Side(R)","8-16 ft.",13,138,-5,1,1],["0029901057",7,1,11,0,"Made Shot","Jump Shot","2PT Field Goal","Mid-Range","Right Side(R)","8-16 ft.",11,106,40,1,1],["0029901057",9,1,10,26,"Missed Shot","Jump Shot","2PT Field Goal","Mid-Range","Left Side(L)","8-16 ft.",10,-106,-3,1,0],["0029901057",185,2,4,30,"Made Shot","Jump Shot","2PT Field Goal","Mid-Range","Left Side(L)","8-16 ft.",15,-149,-33,1,1],["0029901057",230,3,11,41,"Made Shot","Jump Shot","2PT Field Goal","In The Paint (Non-RA)","Center(C)","Less Than 8 ft.",6,-61,-10,1,1],["0029901057",249,3,8,31,"Missed Shot","Jump Shot","2PT Field Goal","Mid-Range","Center(C)","8-16 ft.",14,16,141,1,0],["0029901057",254,3,7,52,"Missed Shot","Jump Shot","2PT Field Goal","Mid-Range","Left Side(L)","8-16 ft.",9,-91,-16,1,0],["0029901057",271,3,6,2,"Made Shot","Jump Shot","2PT Field Goal","In The Paint (Non-RA)","Center(C)","Less Than 8 ft.",7,16,76,1,1],["0029901057",273,3,5,22,"Made Shot","Jump Shot","2PT Field Goal","Mid-Range","Right Side(R)","16-24 ft.",18,186,1,1,1],["0029901057",278,3,4,41,"Missed Shot","Jump Shot","2PT Field Goal","Mid-Range","Right Side(R)","16-24 ft.",17,171,-23,1,0],["0029901057",328,4,10,46,"Missed Shot","Jump Shot","2PT Field Goal","Mid-Range","Left Side(L)","16-24 ft.",16,-166,-33,1,0],["0029901075",18,1,9,57,"Missed Shot","Jump Shot","2PT Field Goal","In The Paint (Non-RA)","Center(C)","Less Than 8 ft.",7,70,-23,1,0],["0029901075",20,1,9,53,"Missed Shot","Layup Shot","2PT Field Goal","Restricted Area","Center(C)","Less Than 8 ft.",0,0,0,1,0],["0029901075",27,1,8,54,"Made Shot","Jump Shot","2PT Field Goal","Mid-Range","Right Side Center(RC)","16-24 ft.",16,85,143,1,1],["0029901075",30,1,8,22,"Made Shot","Jump Shot","2PT Field Goal","Mid-Range","Right Side(R)","8-16 ft.",13,85,102,1,1],["0029901075",224,2,0,11,"Made Shot","Jump Shot","2PT Field Goal","Mid-Range","Left Side(L)","8-16 ft.",15,-158,10,1,1],["0029901075",268,3,5,40,"Made Shot","Jump Shot","2PT Field Goal","Mid-Range","Right Side Center(RC)","16-24 ft.",18,143,124,1,1],["0029901075",272,3,5,4,"Made Shot","Dunk Shot","2PT Field Goal","Restricted Area","Center(C)","Less Than 8 ft.",0,0,0,1,1],["0029901075",277,3,4,37,"Missed Shot","Jump Shot","2PT Field Goal","Mid-Range","Right Side Center(RC)","16-24 ft.",18,143,124,1,0],["0029901075",392,4,6,2,"Made Shot","Jump Shot","2PT Field Goal","Mid-Range","Right Side(R)","8-16 ft.",15,149,-25,1,1],["0029901091",4,1,11,35,"Made Shot","Hook Shot","2PT Field Goal","Restricted Area","Center(C)","Less Than 8 ft.",2,-3,29,1,1],["0029901091",6,1,11,0,"Made Shot","Jump Shot","2PT Field Goal","In The Paint (Non-RA)","Left Side(L)","8-16 ft.",8,-76,-33,1,1],["0029901091",15,1,9,53,"Missed Shot","Jump Shot","2PT Field Goal","Mid-Range","Right Side(R)","16-24 ft.",18,156,104,1,0],["0029901091",46,1,5,41,"Missed Shot","Jump Shot","2PT Field Goal","Mid-Range","Center(C)","8-16 ft.",14,10,141,1,0],["0029901091",225,3,9,29,"Made Shot","Jump Shot","2PT Field Goal","Mid-Range","Center(C)","16-24 ft.",17,31,169,1,1],["0029901091",281,3,2,5,"Made Shot","Jump Shot","2PT Field Goal","In The Paint (Non-RA)","Left Side(L)","8-16 ft.",13,-76,115,1,1],["0029901091",356,4,6,55,"Missed Shot","Jump Shot","2PT Field Goal","In The Paint (Non-RA)","Center(C)","8-16 ft.",12,40,121,1,0],["0029901091",402,4,2,58,"Missed Shot","Jump Shot","2PT Field Goal","Mid-Range","Left Side(L)","8-16 ft.",11,-113,-23,1,0],["0029901109",28,1,8,42,"Made Shot","Jump Shot","2PT Field Goal","In The Paint (Non-RA)","Center(C)","8-16 ft.",11,-25,115,1,1],["0029901109",34,1,7,41,"Missed Shot","Jump Shot","2PT Field Goal","Mid-Range","Right Side(R)","8-16 ft.",14,119,87,1,0],["0029901109",43,1,7,12,"Made Shot","Layup Shot","2PT Field Goal","Restricted Area","Center(C)","Less Than 8 ft.",2,-18,12,1,1],["0029901109",45,1,6,44,"Made Shot","Jump Shot","2PT Field Goal","Mid-Range","Right Side(R)","8-16 ft.",14,91,115,1,1],["0029901109",71,1,3,29,"Missed Shot","Jump Shot","2PT Field Goal","Mid-Range","Right Side(R)","8-16 ft.",15,156,12,1,0],["0029901109",213,2,2,15,"Made Shot","Jump Shot","2PT Field Goal","Mid-Range","Right Side(R)","8-16 ft.",14,149,-10,1,1],["0029901109",261,3,9,42,"Made Shot","Jump Shot","2PT Field Goal","Mid-Range","Left Side(L)","8-16 ft.",14,-98,104,1,1],["0029901109",281,3,7,39,"Made Shot","Jump Shot","2PT Field Goal","Mid-Range","Center(C)","8-16 ft.",15,-61,141,1,1],["0029901109",304,3,4,18,"Made Shot","Jump Shot","2PT Field Goal","In The Paint (Non-RA)","Center(C)","8-16 ft.",13,16,134,1,1],["0029901109",423,4,2,37,"Missed Shot","Layup Shot","2PT Field Goal","Restricted Area","Center(C)","Less Than 8 ft.",1,1,18,1,0],["0029901123",2,1,11,42,"Missed Shot","Jump Shot","2PT Field Goal","Mid-Range","Left Side(L)","8-16 ft.",13,-119,70,1,0],["0029901123",258,3,8,39,"Made Shot","Jump Shot","2PT Field Goal","In The Paint (Non-RA)","Center(C)","8-16 ft.",12,10,126,1,1],["0029901123",272,3,7,21,"Missed Shot","Jump Shot","2PT Field Goal","Mid-Range","Right Side(R)","8-16 ft.",12,117,29,1,0],["0029901123",297,3,4,21,"Made Shot","Jump Shot","2PT Field Goal","Mid-Range","Right Side(R)","8-16 ft.",14,123,81,1,1],["0029901131",30,1,7,34,"Made Shot","Jump Shot","2PT Field Goal","In The Paint (Non-RA)","Center(C)","8-16 ft.",9,46,81,1,1],["0029901131",240,3,9,24,"Missed Shot","Jump Shot","2PT Field Goal","Mid-Range","Left Side(L)","8-16 ft.",15,-156,-8,1,0],["0029901131",252,3,7,28,"Missed Shot","Layup Shot","2PT Field Goal","Restricted Area","Center(C)","Less Than 8 ft.",0,0,0,1,0],["0029901131",291,3,3,16,"Made Shot","Layup Shot","2PT Field Goal","Restricted Area","Center(C)","Less Than 8 ft.",0,0,0,1,1],["0029901131",336,4,10,25,"Missed Shot","Jump Shot","2PT Field Goal","Mid-Range","Left Side(L)","8-16 ft.",11,-104,40,1,0],["0029901131",399,4,4,8,"Made Shot","Jump Shot","2PT Field Goal","Mid-Range","Left Side Center(LC)","16-24 ft.",16,-74,149,1,1],["0029901131",421,4,1,35,"Missed Shot","Jump Shot","2PT Field Goal","Mid-Range","Left Side Center(LC)","16-24 ft.",17,-141,109,1,0],["0029901147",109,1,0,1,"Missed Shot","Layup Shot","2PT Field Goal","Restricted Area","Center(C)","Less Than 8 ft.",2,-18,12,1,0],["0029901147",270,3,6,39,"Missed Shot","Jump Shot","2PT Field Goal","Mid-Range","Right Side(R)","8-16 ft.",14,149,-3,1,0],["0029901166",2,1,11,37,"Missed Shot","Jump Shot","2PT Field Goal","Mid-Range","Left Side(L)","8-16 ft.",13,-134,-10,1,0],["0029901166",7,1,11,3,"Missed Shot","Jump Shot","2PT Field Goal","Mid-Range","Left Side(L)","8-16 ft.",10,-91,57,1,0],["0029901166",22,1,9,57,"Made Shot","Hook Shot","2PT Field Goal","Mid-Range","Right Side(R)","8-16 ft.",11,113,29,1,1],["0029901166",26,1,9,5,"Missed Shot","Jump Shot","2PT Field Goal","Mid-Range","Left Side(L)","8-16 ft.",11,-113,12,1,0],["0029901166",235,2,0,28,"Made Shot","Jump Shot","2PT Field Goal","Mid-Range","Left Side Center(LC)","16-24 ft.",17,-106,141,1,1],["0029901166",299,3,7,18,"Made Shot","Jump Shot","2PT Field Goal","Mid-Range","Center(C)","16-24 ft.",18,25,179,1,1],["0029901166",325,3,5,0,"Made Shot","Jump Shot","2PT Field Goal","Mid-Range","Left Side Center(LC)","16-24 ft.",16,-76,141,1,1],["0029901166",331,3,4,24,"Made Shot","Jump Shot","2PT Field Goal","Mid-Range","Left Side Center(LC)","16-24 ft.",16,-76,145,1,1],["0029901166",401,4,11,46,"Made Shot","Jump Shot","2PT Field Goal","Mid-Range","Right Side(R)","16-24 ft.",16,143,87,1,1],["0029901166",411,4,10,14,"Missed Shot","Jump Shot","2PT Field Goal","Mid-Range","Left Side(L)","8-16 ft.",14,-149,5,1,0],["0029901182",26,1,8,48,"Missed Shot","Jump Shot","2PT Field Goal","Mid-Range","Center(C)","16-24 ft.",16,16,164,1,0],["0029901182",35,1,7,29,"Missed Shot","Hook Shot","2PT Field Goal","In The Paint (Non-RA)","Center(C)","Less Than 8 ft.",4,-40,16,1,0],["0029901182",43,1,6,47,"Made Shot","Layup Shot","2PT Field Goal","Restricted Area","Center(C)","Less Than 8 ft.",0,0,0,1,1],["0029901182",45,1,6,18,"Made Shot","Jump Shot","2PT Field Goal","Mid-Range","Left Side Center(LC)","16-24 ft.",16,-104,126,1,1],["0029901182",184,2,2,58,"Missed Shot","Jump Shot","2PT Field Goal","Mid-Range","Left Side Center(LC)","16-24 ft.",18,-126,136,1,0],["0029901182",195,2,2,11,"Made Shot","Layup Shot","2PT Field Goal","In The Paint (Non-RA)","Center(C)","Less Than 8 ft.",6,68,16,1,1],["0029901182",214,2,0,55,"Missed Shot","Jump Shot","2PT Field Goal","Mid-Range","Left Side(L)","8-16 ft.",10,-83,70,1,0],["0029901182",229,2,0,38,"Missed Shot","Hook Shot","2PT Field Goal","Restricted Area","Center(C)","Less Than 8 ft.",0,0,0,1,0]]}},"GameList":{"29900881":[1562,"0029900881","03/10/2000","WAS","Wizards","SAS","Spurs",4,11,5,12,0,0,4,2,3,0,8],"29900909":[1562,"0029900909","03/14/2000","WAS","Wizards","ORL","Magic",0,8,4,10,0,0,3,1,0,2,5],"29900210":[1562,"0029900210","12/01/1999","WAS","Wizards","CLE","Cavaliers",1,0,0,0,0,0,2,1,0,0,3],"29901166":[1562,"0029901166","04/18/2000","WAS","Wizards","BOS","Celtics",0,12,6,10,0,0,3,0,1,1,6],"29900234":[1562,"0029900234","12/04/1999","WAS","Wizards","SAC","Kings",0,11,4,6,0,0,1,0,0,0,7],"29900258":[1562,"0029900258","12/07/1999","WAS","Wizards","LAL","Lakers",0,4,2,2,0,0,1,0,0,1,1],"29900270":[1562,"0029900270","12/09/1999","WAS","Wizards","PHX","Suns",1,8,4,6,0,0,0,0,0,2,4],"29900790":[1562,"0029900790","02/26/2000","WAS","Wizards","MIA","Heat",0,2,1,4,0,0,2,0,0,0,1],"29900772":[1562,"0029900772","02/24/2000","WAS","Wizards","PHX","Suns",0,0,0,0,0,0,1,0,0,1,2],"29900119":[1562,"0029900119","11/18/1999","WAS","Wizards","TOR","Raptors",0,6,2,4,0,0,4,0,3,0,5],"29900466":[1562,"0029900466","01/08/2000","WAS","Wizards","MIL","Bucks",0,0,0,1,0,0,0,0,0,1,0],"29900357":[1562,"0029900357","12/21/1999","WAS","Wizards","DET","Pistons",0,2,1,1,0,0,1,0,0,0,1],"29900444":[1562,"0029900444","01/05/2000","WAS","Wizards","CHI","Bulls",0,4,2,5,0,0,0,1,1,1,4],"29900036":[1562,"0029900036","11/06/1999","WAS","Wizards","ORL","Magic",2,2,1,2,0,0,0,1,0,0,1],"29901109":[1562,"0029901109","04/10/2000","WAS","Wizards","CHH","Hornets",1,14,7,10,0,0,4,0,1,2,4],"29900426":[1562,"0029900426","01/03/2000","WAS","Wizards","GSW","Warriors",0,0,0,1,0,0,0,0,0,0,0],"29900290":[1562,"0029900290","12/11/1999","WAS","Wizards","SAS","Spurs",1,0,0,1,0,0,0,0,0,0,2],"29900837":[1562,"0029900837","03/04/2000","WAS","Wizards","DET","Pistons",0,11,5,8,0,0,2,0,0,1,5],"29900014":[1562,"0029900014","11/03/1999","WAS","Wizards","BOS","Celtics",0,5,2,3,0,0,1,0,0,0,3],"29900075":[1562,"0029900075","11/12/1999","WAS","Wizards","MIA","Heat",0,10,4,7,0,0,2,0,3,0,9],"29900406":[1562,"0029900406","12/29/1999","WAS","Wizards","CLE","Cavaliers",0,0,0,1,0,0,0,0,0,0,2],"29900818":[1562,"0029900818","03/01/2000","WAS","Wizards","ATL","Hawks",1,17,8,9,0,0,3,0,2,1,8],"29900298":[1562,"0029900298","12/14/1999","WAS","Wizards","UTA","Jazz",0,1,0,0,0,0,0,0,0,0,1],"29900173":[1562,"0029900173","11/26/1999","WAS","Wizards","CHH","Hornets",1,4,2,2,0,0,1,0,0,1,2],"29901182":[1562,"0029901182","04/19/2000","WAS","Wizards","MIL","Bucks",1,7,3,8,0,0,5,0,0,1,9],"29900153":[1562,"0029900153","11/23/1999","WAS","Wizards","VAN","Grizzlies",1,5,2,4,0,0,1,1,0,0,2],"29900100":[1562,"0029900100","11/16/1999","WAS","Wizards","PHI","76ers",2,1,0,3,0,0,2,0,0,1,4],"29901147":[1562,"0029901147","04/15/2000","WAS","Wizards","MIL","Bucks",0,0,0,2,0,0,4,0,0,0,6],"29900852":[1562,"0029900852","03/06/2000","WAS","Wizards","ORL","Magic",1,5,1,3,0,0,4,2,2,2,12],"29900250":[1562,"0029900250","12/06/1999","WAS","Wizards","UTA","Jazz",0,2,1,1,0,0,2,0,0,0,1],"29900960":[1562,"0029900960","03/20/2000","WAS","Wizards","LAC","Clippers",0,0,0,4,0,0,2,0,1,1,8],"29900584":[1562,"0029900584","03/08/2000","WAS","Wizards","NYK","Knicks",0,12,4,6,0,0,3,0,1,2,9],"29900862":[1562,"0029900862","03/07/2000","WAS","Wizards","MIN","Timberwolves",0,6,3,6,0,0,3,1,1,1,3],"29900486":[1562,"0029900486","01/11/2000","WAS","Wizards","TOR","Raptors",0,4,0,1,0,0,1,0,0,1,1],"29900995":[1562,"0029900995","03/25/2000","WAS","Wizards","DAL","Mavericks",2,4,2,6,0,0,3,0,0,1,2],"29901033":[1562,"0029901033","03/31/2000","WAS","Wizards","BOS","Celtics",1,2,1,1,0,0,1,0,1,0,1],"29900135":[1562,"0029900135","11/20/1999","WAS","Wizards","LAC","Clippers",2,3,1,2,0,0,0,0,0,0,4],"29900084":[1562,"0029900084","11/13/1999","WAS","Wizards","IND","Pacers",0,20,9,15,0,0,3,0,2,0,16],"29900898":[1562,"0029900898","03/12/2000","WAS","Wizards","POR","Trail Blazers",1,8,3,10,0,0,3,0,1,2,5],"29901131":[1562,"0029901131","04/13/2000","WAS","Wizards","CHI","Bulls",1,12,3,7,0,0,5,0,1,2,9],"29901075":[1562,"0029901075","04/06/2000","WAS","Wizards","NYK","Knicks",1,12,6,9,0,0,6,0,0,3,8],"29900225":[1562,"0029900225","12/03/1999","WAS","Wizards","TOR","Raptors",0,0,0,0,0,0,1,0,0,0,0],"29901057":[1562,"0029901057","04/04/2000","WAS","Wizards","NJN","Nets",2,10,5,10,0,0,5,0,0,0,6],"29900457":[1562,"0029900457","01/07/2000","WAS","Wizards","CHI","Bulls",2,6,3,4,0,0,4,0,1,0,0],"29900062":[1562,"0029900062","11/10/1999","WAS","Wizards","SEA","SuperSonics",0,0,0,0,0,0,0,1,0,0,2],"29900413":[1562,"0029900413","12/30/1999","WAS","Wizards","NYK","Knicks",0,0,0,1,0,0,0,0,0,0,0],"29900517":[1562,"0029900517","01/15/2000","WAS","Wizards","DET","Pistons",1,0,0,0,0,0,0,0,0,0,1],"29900201":[1562,"0029900201","11/30/1999","WAS","Wizards","NJN","Nets",2,2,1,1,0,0,2,0,0,0,1],"29901091":[1562,"0029901091","04/08/2000","WAS","Wizards","ATL","Hawks",1,10,4,8,0,0,4,2,4,2,9],"29900381":[1562,"0029900381","12/26/1999","WAS","Wizards","HOU","Rockets",0,0,0,0,0,0,0,0,0,0,1],"29900003":[1562,"0029900003","11/02/1999","WAS","Wizards","ATL","Hawks",1,11,5,7,0,0,1,0,0,2,2],"29901123":[1562,"0029901123","04/12/2000","WAS","Wizards","PHI","76ers",0,4,2,4,0,0,4,1,0,4,2],"29900940":[1562,"0029900940","03/18/2000","WAS","Wizards","CHI","Bulls",1,12,5,9,0,0,4,0,1,1,10],"29900161":[1562,"0029900161","11/24/1999","WAS","Wizards","PHI","76ers",0,2,1,2,0,0,3,0,1,0,1],"29900923":[1562,"0029900923","03/16/2000","WAS","Wizards","LAL","Lakers",0,11,5,8,0,0,5,0,0,1,4],"29900046":[1562,"0029900046","11/07/1999","WAS","Wizards","NJN","Nets",0,5,1,4,0,0,1,1,0,0,2],"29900823":[1562,"0029900823","03/02/2000","WAS","Wizards","PHI","76ers",0,8,3,9,0,0,3,0,0,1,5],"29900967":[1562,"0029900967","03/21/2000","WAS","Wizards","SAC","Kings",2,3,1,6,0,0,5,0,1,2,6],"29901020":[1562,"0029901020","03/29/2000","WAS","Wizards","DEN","Nuggets",2,4,2,5,0,0,2,0,1,2,3],"29900372":[1562,"0029900372","12/23/1999","WAS","Wizards","HOU","Rockets",0,0,0,0,0,0,0,0,1,0,1],"29900495":[1562,"0029900495","01/12/2000","WAS","Wizards","IND","Pacers",1,0,0,1,0,0,1,0,0,0,1],"29900982":[1562,"0029900982","03/23/2000","WAS","Wizards","DEN","Nuggets",1,4,2,5,0,0,4,0,0,3,9]},"data":[27.0,62,28,17.1,2.2,4.5,0.502,0.0,0.0,0.0,0.8,1.1,0.742,1.4,2.7,4.0,0.8,0.5,0.2,0.7,2.1,5.3],"rank":{"PerGame":[null,null,null,null,null,null,null,null,null,null,null,null,null,null,null,null,null,null,null],"Totals":[237,236,254,null,281,355,null,250,256,null,135,192,172,266,213,205,273,247,220]},"team":"WAS"},"1998":{"shotchart":{"Averages":{"header":["SHOT_ZONE_BASIC","SHOT_ZONE_AREA","SHOT_ZONE_RANGE","FGA","FGM","FG_PCT"],"row":[["Above the Break 3","Back Court(BC)","Back Court Shot",75,2,0.027],["Above the Break 3","Center(C)","24+ ft.",3050,962,0.315],["Above the Break 3","Left Side Center(LC)","24+ ft.",5658,1877,0.332],["Above the Break 3","Right Side Center(RC)","24+ ft.",5982,2051,0.343],["Backcourt","Back Court(BC)","Back Court Shot",144,4,0.028],["In The Paint (Non-RA)","Center(C)","8-16 ft.",2904,1157,0.398],["In The Paint (Non-RA)","Center(C)","Less Than 8 ft.",12080,4295,0.356],["In The Paint (Non-RA)","Left Side(L)","8-16 ft.",1130,400,0.354],["In The Paint (Non-RA)","Right Side(R)","8-16 ft.",1094,385,0.352],["Left Corner 3","Left Side(L)","24+ ft.",2119,812,0.383],["Mid-Range","Center(C)","16-24 ft.",3601,1425,0.396],["Mid-Range","Center(C)","8-16 ft.",1269,570,0.449],["Mid-Range","Left Side Center(LC)","16-24 ft.",4680,1830,0.391],["Mid-Range","Left Side(L)","16-24 ft.",5864,2295,0.391],["Mid-Range","Left Side(L)","8-16 ft.",9034,3276,0.363],["Mid-Range","Right Side Center(RC)","16-24 ft.",4827,1907,0.395],["Mid-Range","Right Side(R)","16-24 ft.",5416,2112,0.39],["Mid-Range","Right Side(R)","8-16 ft.",7334,2564,0.35],["Restricted Area","Center(C)","Less Than 8 ft.",35102,20893,0.595],["Right Corner 3","Right Side(R)","24+ ft.",2011,731,0.364]]},"Details":{"header":["GAME_ID","GAME_EVENT_ID","PERIOD","MINUTES_REMAINING","SECONDS_REMAINING","EVENT_TYPE","ACTION_TYPE","SHOT_TYPE","SHOT_ZONE_BASIC","SHOT_ZONE_AREA","SHOT_ZONE_RANGE","SHOT_DISTANCE","LOC_X","LOC_Y","SHOT_ATTEMPTED_FLAG","SHOT_MADE_FLAG"],"row":[["0029800007",476,4,5,39,"Missed Shot","Jump Shot","2PT Field Goal","Mid-Range","Left Side(L)","8-16 ft.",9,-81,46,1,0],["0029800112",118,2,11,11,"Made Shot","Slam Dunk Shot","2PT Field Goal","Restricted Area","Center(C)","Less Than 8 ft.",0,0,0,1,1],["0029800112",267,3,9,27,"Missed Shot","Jump Shot","2PT Field Goal","Mid-Range","Center(C)","16-24 ft.",17,-6,175,1,0],["0029800183",494,4,1,33,"Missed Shot","Jump Shot","2PT Field Goal","Mid-Range","Center(C)","8-16 ft.",14,31,139,1,0],["0029800183",503,4,0,46,"Made Shot","Layup Shot","2PT Field Goal","Restricted Area","Center(C)","Less Than 8 ft.",2,-18,12,1,1],["0029800516",424,4,3,18,"Made Shot","Layup Shot","2PT Field Goal","Restricted Area","Center(C)","Less Than 8 ft.",0,0,0,1,1],["0029800532",437,4,2,36,"Missed Shot","Jump Shot","2PT Field Goal","In The Paint (Non-RA)","Center(C)","8-16 ft.",9,25,91,1,0],["0029800551",425,4,3,42,"Missed Shot","Jump Shot","2PT Field Goal","Mid-Range","Left Side(L)","8-16 ft.",8,-81,16,1,0],["0029800551",451,4,1,36,"Made Shot","Jump Shot","2PT Field Goal","Mid-Range","Left Side(L)","8-16 ft.",10,-100,16,1,1],["0029800616",417,4,3,51,"Made Shot","Jump Shot","2PT Field Goal","Mid-Range","Left Side(L)","8-16 ft.",10,-109,-1,1,1],["0029800629",445,4,1,25,"Missed Shot","Jump Shot","2PT Field Goal","Mid-Range","Right Side(R)","8-16 ft.",13,132,21,1,0],["0029800629",454,4,0,30,"Missed Shot","Hook Shot","2PT Field Goal","Restricted Area","Center(C)","Less Than 8 ft.",0,0,0,1,0],["0029800629",456,4,0,28,"Made Shot","Layup Shot","2PT Field Goal","Restricted Area","Center(C)","Less Than 8 ft.",0,0,0,1,1],["0029800674",413,4,1,47,"Missed Shot","Jump Shot","2PT Field Goal","Mid-Range","Left Side(L)","8-16 ft.",11,-119,14,1,0]]}},"GameList":{"29800674":[1562,"0029800674","04/29/1999","SAS","Spurs","VAN","Grizzlies",1,2,0,1,0,0,1,0,0,2,1],"29800551":[1562,"0029800551","04/14/1999","SAS","Spurs","MIN","Timberwolves",1,5,1,2,0,0,2,0,0,0,2],"29800629":[1562,"0029800629","04/24/1999","SAS","Spurs","LAL","Lakers",0,3,1,3,0,0,1,0,0,0,2],"29800516":[1562,"0029800516","04/10/1999","SAS","Spurs","PHX","Suns",0,2,1,1,0,0,0,0,1,0,2],"29800532":[1562,"0029800532","04/12/1999","SAS","Spurs","PHX","Suns",0,0,0,1,0,0,0,1,0,0,0],"29800616":[1562,"0029800616","04/22/1999","SAS","Spurs","DAL","Mavericks",0,5,1,1,0,0,1,0,1,1,0],"29800054":[1562,"0029800054","02/11/1999","SAS","Spurs","CLE","Cavaliers",0,0,0,0,0,0,1,0,0,0,0],"29800034":[1562,"0029800034","02/08/1999","SAS","Spurs","LAL","Lakers",1,0,0,0,0,0,1,0,0,0,0],"29800152":[1562,"0029800152","02/24/1999","SAS","Spurs","SEA","SuperSonics",0,0,0,0,0,0,0,0,0,0,0],"29800007":[1562,"0029800007","02/05/1999","SAS","Spurs","SAC","Kings",1,0,0,1,0,0,1,0,0,0,1],"29800129":[1562,"0029800129","02/21/1999","SAS","Spurs","DET","Pistons",0,0,0,0,0,0,0,0,0,0,0],"29800112":[1562,"0029800112","02/19/1999","SAS","Spurs","LAL","Lakers",0,3,1,2,0,0,3,0,0,0,2],"29800648":[1562,"0029800648","04/26/1999","SAS","Spurs","LAC","Clippers",0,0,0,0,0,0,0,0,0,0,0],"29800171":[1562,"0029800171","02/26/1999","SAS","Spurs","SEA","SuperSonics",0,0,0,0,0,0,1,0,0,1,0],"29800069":[1562,"0029800069","02/14/1999","SAS","Spurs","CHI","Bulls",0,0,0,0,0,0,0,0,0,0,0],"29800062":[1562,"0029800062","02/12/1999","SAS","Spurs","PHI","76ers",0,0,0,0,0,0,0,0,0,0,0],"29800040":[1562,"0029800040","02/09/1999","SAS","Spurs","MIN","Timberwolves",0,0,0,0,0,0,0,0,0,0,1],"29800018":[1562,"0029800018","02/06/1999","SAS","Spurs","MIN","Timberwolves",0,1,0,0,0,0,0,0,0,0,0],"29800183":[1562,"0029800183","02/28/1999","SAS","Spurs","UTA","Jazz",0,2,1,2,0,0,0,0,0,0,3]},"data":[26.0,19,0,3.3,0.3,0.7,0.429,0.0,0.0,0.0,0.6,0.9,0.611,0.3,0.4,0.7,0.2,0.1,0.1,0.2,0.6,1.2],"rank":{"PerGame":[null,null,null,null,null,null,null,null,null,null,null,null,null,null,null,null,null,null,null],"Totals":[380,375,385,null,255,339,null,328,324,null,348,375,368,358,370,339,382,370,364]},"team":"SAS"},"2000":{"shotchart":{"Averages":{"header":["SHOT_ZONE_BASIC","SHOT_ZONE_AREA","SHOT_ZONE_RANGE","FGA","FGM","FG_PCT"],"row":[["Above the Break 3","Back Court(BC)","Back Court Shot",116,5,0.043],["Above the Break 3","Center(C)","24+ ft.",5091,1727,0.339],["Above the Break 3","Left Side Center(LC)","24+ ft.",9506,3300,0.347],["Above the Break 3","Right Side Center(RC)","24+ ft.",9469,3381,0.357],["Backcourt","Back Court(BC)","Back Court Shot",298,13,0.044],["In The Paint (Non-RA)","Center(C)","8-16 ft.",5907,2353,0.398],["In The Paint (Non-RA)","Center(C)","Less Than 8 ft.",19915,7109,0.357],["In The Paint (Non-RA)","Left Side(L)","8-16 ft.",2160,855,0.396],["In The Paint (Non-RA)","Right Side(R)","8-16 ft.",2081,811,0.39],["Left Corner 3","Left Side(L)","24+ ft.",3993,1520,0.381],["Mid-Range","Center(C)","16-24 ft.",5774,2350,0.407],["Mid-Range","Center(C)","8-16 ft.",1667,673,0.404],["Mid-Range","Left Side Center(LC)","16-24 ft.",8627,3463,0.401],["Mid-Range","Left Side(L)","16-24 ft.",11007,4379,0.398],["Mid-Range","Left Side(L)","8-16 ft.",14611,5526,0.378],["Mid-Range","Right Side Center(RC)","16-24 ft.",9284,3743,0.403],["Mid-Range","Right Side(R)","16-24 ft.",9721,3849,0.396],["Mid-Range","Right Side(R)","8-16 ft.",11996,4434,0.37],["Restricted Area","Center(C)","Less Than 8 ft.",56347,33814,0.6],["Right Corner 3","Right Side(R)","24+ ft.",4092,1559,0.381]]},"Details":{"header":["GAME_ID","GAME_EVENT_ID","PERIOD","MINUTES_REMAINING","SECONDS_REMAINING","EVENT_TYPE","ACTION_TYPE","SHOT_TYPE","SHOT_ZONE_BASIC","SHOT_ZONE_AREA","SHOT_ZONE_RANGE","SHOT_DISTANCE","LOC_X","LOC_Y","SHOT_ATTEMPTED_FLAG","SHOT_MADE_FLAG"],"row":[["0020000003",141,2,10,15,"Made Shot","Layup Shot","2PT Field Goal","Restricted Area","Center(C)","Less Than 8 ft.",0,0,0,1,1],["0020000003",265,2,1,6,"Made Shot","Layup Shot","2PT Field Goal","Restricted Area","Center(C)","Less Than 8 ft.",0,0,0,1,1],["0020000003",382,3,0,3,"Made Shot","Jump Shot","2PT Field Goal","Mid-Range","Right Side(R)","16-24 ft.",17,176,-23,1,1],["0020000017",142,2,10,1,"Made Shot","Jump Shot","2PT Field Goal","Mid-Range","Left Side(L)","16-24 ft.",17,-176,19,1,1],["0020000037",214,2,6,11,"Made Shot","Hook Shot","2PT Field Goal","In The Paint (Non-RA)","Center(C)","Less Than 8 ft.",4,1,47,1,1],["0020000037",250,2,3,36,"Made Shot","Turnaround Jump Shot","2PT Field Goal","Mid-Range","Right Side(R)","8-16 ft.",9,85,36,1,1],["0020000037",282,2,0,46,"Missed Shot","Jump Shot","2PT Field Goal","Mid-Range","Right Side Center(RC)","16-24 ft.",17,123,125,1,0],["0020000037",285,2,0,4,"Missed Shot","Jump Shot","2PT Field Goal","Mid-Range","Right Side(R)","16-24 ft.",16,167,0,1,0],["0020000037",296,3,11,9,"Missed Shot","Jump Shot","2PT Field Goal","Mid-Range","Center(C)","16-24 ft.",20,16,200,1,0],["0020000037",346,3,6,34,"Made Shot","Driving Layup Shot","2PT Field Goal","Restricted Area","Center(C)","Less Than 8 ft.",0,0,0,1,1],["0020000037",384,3,3,15,"Made Shot","Turnaround Jump Shot","2PT Field Goal","In The Paint (Non-RA)","Center(C)","Less Than 8 ft.",7,64,36,1,1],["0020000037",392,3,2,22,"Missed Shot","Jump Shot","2PT Field Goal","Mid-Range","Left Side(L)","8-16 ft.",11,-113,15,1,0],["0020000056",134,2,11,43,"Missed Shot","Jump Shot","2PT Field Goal","Mid-Range","Right Side(R)","8-16 ft.",10,100,7,1,0],["0020000056",550,4,1,20,"Made Shot","Layup Shot","2PT Field Goal","Restricted Area","Center(C)","Less Than 8 ft.",0,0,0,1,1],["0020000063",191,2,3,3,"Missed Shot","Jump Shot","2PT Field Goal","Mid-Range","Right Side(R)","16-24 ft.",16,161,-17,1,0],["0020000063",387,4,8,25,"Made Shot","Hook Shot","2PT Field Goal","In The Paint (Non-RA)","Center(C)","Less Than 8 ft.",4,-8,42,1,1],["0020000080",24,1,8,20,"Made Shot","Layup Shot","2PT Field Goal","Restricted Area","Center(C)","Less Than 8 ft.",1,11,15,1,1],["0020000080",42,1,5,45,"Missed Shot","Jump Shot","2PT Field Goal","Mid-Range","Right Side(R)","8-16 ft.",15,153,4,1,0],["0020000080",258,3,7,36,"Made Shot","Running Jump Shot","2PT Field Goal","In The Paint (Non-RA)","Center(C)","Less Than 8 ft.",5,3,53,1,1],["0020000089",25,1,7,58,"Made Shot","Jump Shot","2PT Field Goal","Mid-Range","Left Side(L)","16-24 ft.",17,-176,-27,1,1],["0020000089",36,1,6,9,"Missed Shot","Jump Shot","2PT Field Goal","Mid-Range","Right Side(R)","16-24 ft.",18,180,-34,1,0],["0020000089",252,3,11,43,"Made Shot","Jump Shot","2PT Field Goal","Mid-Range","Left Side(L)","8-16 ft.",13,-130,-13,1,1],["0020000089",355,3,2,1,"Missed Shot","Jump Shot","2PT Field Goal","Restricted Area","Center(C)","Less Than 8 ft.",3,-8,34,1,0],["0020000089",356,3,1,56,"Made Shot","Layup Shot","2PT Field Goal","Restricted Area","Center(C)","Less Than 8 ft.",2,3,28,1,1],["0020000089",362,3,1,6,"Made Shot","Layup Shot","2PT Field Goal","Restricted Area","Center(C)","Less Than 8 ft.",0,-1,-8,1,1],["0020000089",471,4,5,4,"Missed Shot","Layup Shot","2PT Field Goal","Restricted Area","Center(C)","Less Than 8 ft.",2,18,17,1,0],["0020000111",3,1,11,16,"Missed Shot","Jump Shot","2PT Field Goal","Mid-Range","Right Side(R)","16-24 ft.",20,205,-32,1,0],["0020000119",112,2,11,4,"Made Shot","Turnaround Jump Shot","2PT Field Goal","Mid-Range","Left Side(L)","8-16 ft.",10,-109,-6,1,1],["0020000119",139,2,7,44,"Made Shot","Jump Shot","2PT Field Goal","Mid-Range","Left Side(L)","16-24 ft.",16,-151,57,1,1],["0020000119",151,2,6,29,"Missed Shot","Jump Shot","2PT Field Goal","Mid-Range","Left Side(L)","8-16 ft.",15,-151,0,1,0],["0020000119",164,2,4,18,"Missed Shot","Jump Shot","2PT Field Goal","In The Paint (Non-RA)","Center(C)","Less Than 8 ft.",4,47,9,1,0],["0020000135",211,2,2,53,"Missed Shot","Jump Shot","2PT Field Goal","In The Paint (Non-RA)","Left Side(L)","8-16 ft.",12,-79,97,1,0],["0020000135",424,4,6,29,"Made Shot","Jump Shot","2PT Field Goal","In The Paint (Non-RA)","Center(C)","Less Than 8 ft.",7,-71,0,1,1],["0020000135",438,4,4,39,"Missed Shot","Jump Shot","2PT Field Goal","In The Paint (Non-RA)","Center(C)","8-16 ft.",8,3,87,1,0],["0020000135",467,4,1,8,"Missed Shot","Jump Shot","2PT Field Goal","In The Paint (Non-RA)","Center(C)","Less Than 8 ft.",7,-79,-6,1,0],["0020000153",123,2,10,8,"Made Shot","Jump Shot","2PT Field Goal","Mid-Range","Right Side(R)","8-16 ft.",10,98,36,1,1],["0020000175",111,1,0,28,"Made Shot","Jump Shot","2PT Field Goal","Mid-Range","Right Side(R)","8-16 ft.",15,155,13,1,1],["0020000175",121,2,11,31,"Missed Shot","Jump Shot","2PT Field Goal","Mid-Range","Left Side(L)","16-24 ft.",18,-183,-8,1,0],["0020000175",134,2,9,16,"Made Shot","Driving Layup Shot","2PT Field Goal","Restricted Area","Center(C)","Less Than 8 ft.",2,16,19,1,1],["0020000175",195,2,3,41,"Missed Shot","Jump Shot","2PT Field Goal","Mid-Range","Left Side Center(LC)","16-24 ft.",19,-124,144,1,0],["0020000183",392,4,11,17,"Made Shot","Jump Shot","2PT Field Goal","Mid-Range","Right Side(R)","16-24 ft.",19,197,-23,1,1],["0020000183",401,4,9,31,"Made Shot","Jump Shot","2PT Field Goal","Mid-Range","Left Side(L)","8-16 ft.",15,-151,-27,1,1],["0020000183",409,4,8,32,"Made Shot","Dunk Shot","2PT Field Goal","Restricted Area","Center(C)","Less Than 8 ft.",1,-16,-6,1,1],["0020000183",429,4,6,29,"Missed Shot","Jump Shot","2PT Field Goal","In The Paint (Non-RA)","Right Side(R)","8-16 ft.",10,56,87,1,0],["0020000183",455,4,3,38,"Missed Shot","Jump Shot","2PT Field Goal","Restricted Area","Center(C)","Less Than 8 ft.",3,-29,19,1,0],["0020000200",117,2,11,41,"Missed Shot","Jump Shot","2PT Field Goal","Mid-Range","Left Side(L)","8-16 ft.",9,-94,-6,1,0],["0020000200",173,2,6,32,"Missed Shot","Jump Shot","2PT Field Goal","Mid-Range","Left Side(L)","16-24 ft.",18,-178,-27,1,0],["0020000200",211,2,2,11,"Missed Shot","Jump Shot","2PT Field Goal","Mid-Range","Right Side(R)","8-16 ft.",15,153,-6,1,0],["0020000200",234,2,0,10,"Missed Shot","Jump Shot","2PT Field Goal","Mid-Range","Right Side(R)","16-24 ft.",17,176,-27,1,0],["0020000200",361,3,1,0,"Missed Shot","Layup Shot","2PT Field Goal","Restricted Area","Center(C)","Less Than 8 ft.",2,-23,4,1,0],["0020000209",142,2,8,49,"Missed Shot","Jump Shot","2PT Field Goal","In The Paint (Non-RA)","Center(C)","8-16 ft.",8,16,85,1,0],["0020000209",324,3,1,42,"Made Shot","Jump Shot","2PT Field Goal","In The Paint (Non-RA)","Left Side(L)","8-16 ft.",10,-73,80,1,1],["0020000235",13,1,10,23,"Made Shot","Jump Shot","2PT Field Goal","Mid-Range","Left Side(L)","8-16 ft.",14,-145,9,1,1],["0020000235",26,1,7,28,"Made Shot","Jump Shot","2PT Field Goal","Mid-Range","Left Side(L)","8-16 ft.",13,-124,42,1,1],["0020000235",50,1,5,45,"Made Shot","Jump Shot","2PT Field Goal","Mid-Range","Right Side(R)","16-24 ft.",16,161,-23,1,1],["0020000235",92,1,2,9,"Made Shot","Tip Shot","2PT Field Goal","Restricted Area","Center(C)","Less Than 8 ft.",0,3,-6,1,1],["0020000243",96,1,1,54,"Made Shot","Jump Shot","2PT Field Goal","Mid-Range","Left Side(L)","16-24 ft.",17,-145,91,1,1],["0020000243",113,1,0,29,"Missed Shot","Jump Shot","2PT Field Goal","Mid-Range","Left Side(L)","16-24 ft.",16,-166,0,1,0],["0020000243",131,2,10,24,"Made Shot","Layup Shot","2PT Field Goal","Restricted Area","Center(C)","Less Than 8 ft.",0,0,0,1,1],["0020000243",170,2,7,14,"Missed Shot","Layup Shot","2PT Field Goal","Restricted Area","Center(C)","Less Than 8 ft.",0,0,0,1,0],["0020000243",331,3,3,52,"Missed Shot","Tip Shot","2PT Field Goal","Restricted Area","Center(C)","Less Than 8 ft.",0,0,0,1,0],["0020000243",370,3,0,51,"Made Shot","Jump Shot","2PT Field Goal","Mid-Range","Center(C)","8-16 ft.",15,24,152,1,1],["0020000243",388,4,11,22,"Missed Shot","Jump Shot","2PT Field Goal","Mid-Range","Center(C)","16-24 ft.",18,-1,186,1,0],["0020000243",392,4,10,51,"Made Shot","Layup Shot","2PT Field Goal","Restricted Area","Center(C)","Less Than 8 ft.",0,0,0,1,1],["0020000243",427,4,6,36,"Made Shot","Jump Shot","2PT Field Goal","Mid-Range","Left Side(L)","8-16 ft.",13,-130,0,1,1],["0020000243",482,4,1,46,"Made Shot","Jump Shot","2PT Field Goal","Mid-Range","Center(C)","8-16 ft.",15,-29,148,1,1],["0020000243",499,4,0,20,"Missed Shot","Jump Shot","2PT Field Goal","Mid-Range","Right Side(R)","8-16 ft.",15,153,40,1,0],["0020000262",122,1,0,25,"Missed Shot","Layup Shot","2PT Field Goal","Restricted Area","Center(C)","Less Than 8 ft.",1,-16,9,1,0],["0020000262",135,2,11,18,"Made Shot","Jump Shot","2PT Field Goal","Mid-Range","Right Side(R)","8-16 ft.",11,110,47,1,1],["0020000272",128,2,9,40,"Made Shot","Turnaround Jump Shot","2PT Field Goal","Mid-Range","Left Side(L)","8-16 ft.",12,-122,-2,1,1],["0020000272",134,2,8,57,"Missed Shot","Jump Shot","2PT Field Goal","Mid-Range","Right Side(R)","8-16 ft.",13,138,19,1,0],["0020000272",373,4,6,9,"Missed Shot","Jump Shot","2PT Field Goal","Mid-Range","Left Side(L)","16-24 ft.",18,-168,80,1,0],["0020000287",121,2,11,25,"Missed Shot","Jump Shot","2PT Field Goal","Mid-Range","Left Side(L)","16-24 ft.",19,-178,87,1,0],["0020000287",416,4,8,27,"Made Shot","Jump Shot","2PT Field Goal","Mid-Range","Left Side(L)","8-16 ft.",9,-94,0,1,1],["0020000287",443,4,6,30,"Made Shot","Layup Shot","2PT Field Goal","Restricted Area","Center(C)","Less Than 8 ft.",3,32,-6,1,1],["0020000313",356,3,4,4,"Missed Shot","Layup Shot","2PT Field Goal","Restricted Area","Center(C)","Less Than 8 ft.",2,-23,15,1,0],["0020000313",408,3,0,37,"Made Shot","Jump Shot","2PT Field Goal","Mid-Range","Left Side(L)","8-16 ft.",14,-145,26,1,1],["0020000313",529,4,1,35,"Made Shot","Layup Shot","2PT Field Goal","Restricted Area","Center(C)","Less Than 8 ft.",1,-8,9,1,1],["0020000313",532,4,1,2,"Missed Shot","Jump Shot","2PT Field Goal","Mid-Range","Left Side(L)","16-24 ft.",17,-172,0,1,0],["0020000328",110,1,0,0,"Made Shot","Layup Shot","2PT Field Goal","Mid-Range","Left Side(L)","8-16 ft.",10,-94,47,1,1],["0020000328",127,2,10,0,"Made Shot","Layup Shot","2PT Field Goal","Restricted Area","Center(C)","Less Than 8 ft.",2,18,15,1,1],["0020000328",131,2,9,13,"Missed Shot","Jump Shot","2PT Field Goal","In The Paint (Non-RA)","Center(C)","Less Than 8 ft.",4,18,36,1,0],["0020000328",141,2,8,23,"Missed Shot","Jump Shot","2PT Field Goal","Mid-Range","Right Side(R)","8-16 ft.",12,125,26,1,0],["0020000328",302,3,6,7,"Made Shot","Jump Shot","2PT Field Goal","Mid-Range","Right Side(R)","8-16 ft.",15,153,9,1,1],["0020000328",323,3,3,5,"Made Shot","Jump Shot","2PT Field Goal","Mid-Range","Right Side(R)","16-24 ft.",18,167,70,1,1],["0020000328",336,3,2,12,"Made Shot","Jump Shot","2PT Field Goal","Mid-Range","Right Side(R)","8-16 ft.",15,153,4,1,1],["0020000328",353,3,0,46,"Missed Shot","Jump Shot","2PT Field Goal","Mid-Range","Left Side(L)","8-16 ft.",15,-151,19,1,0],["0020000328",419,4,7,20,"Made Shot","Reverse Layup Shot","2PT Field Goal","Restricted Area","Center(C)","Less Than 8 ft.",3,39,4,1,1],["0020000328",430,4,5,47,"Made Shot","Jump Shot","2PT Field Goal","Mid-Range","Right Side(R)","8-16 ft.",15,153,36,1,1],["0020000328",451,4,3,22,"Missed Shot","Jump Shot","2PT Field Goal","In The Paint (Non-RA)","Center(C)","Less Than 8 ft.",7,68,19,1,0],["0020000328",456,4,2,53,"Made Shot","Dunk Shot","2PT Field Goal","Restricted Area","Center(C)","Less Than 8 ft.",1,-1,19,1,1],["0020000349",58,1,4,53,"Missed Shot","Jump Shot","2PT Field Goal","Mid-Range","Left Side(L)","16-24 ft.",18,-185,11,1,0],["0020000349",77,1,3,27,"Missed Shot","Jump Shot","2PT Field Goal","In The Paint (Non-RA)","Center(C)","Less Than 8 ft.",7,-71,15,1,0],["0020000349",81,1,3,15,"Made Shot","Driving Layup Shot","2PT Field Goal","Restricted Area","Center(C)","Less Than 8 ft.",0,0,0,1,1],["0020000349",104,1,2,6,"Missed Shot","Jump Shot","2PT Field Goal","In The Paint (Non-RA)","Center(C)","Less Than 8 ft.",4,22,34,1,0],["0020000349",106,1,2,4,"Missed Shot","Layup Shot","2PT Field Goal","Restricted Area","Center(C)","Less Than 8 ft.",3,30,15,1,0],["0020000349",289,3,11,5,"Made Shot","Jump Shot","2PT Field Goal","Mid-Range","Left Side(L)","8-16 ft.",14,-141,34,1,1],["0020000349",418,4,8,32,"Made Shot","Jump Shot","2PT Field Goal","Mid-Range","Right Side(R)","16-24 ft.",18,188,0,1,1],["0020000349",450,4,4,55,"Missed Shot","Jump Shot","2PT Field Goal","Mid-Range","Right Side(R)","8-16 ft.",15,159,-4,1,0],["0020000349",496,4,0,35,"Missed Shot","Jump Shot","2PT Field Goal","Mid-Range","Right Side(R)","8-16 ft.",14,144,11,1,0],["0020000359",144,2,11,47,"Missed Shot","Jump Shot","2PT Field Goal","Mid-Range","Left Side(L)","16-24 ft.",17,-168,47,1,0],["0020000359",154,2,10,36,"Made Shot","Running Jump Shot","2PT Field Goal","In The Paint (Non-RA)","Center(C)","Less Than 8 ft.",5,56,13,1,1],["0020000359",188,2,6,55,"Missed Shot","Jump Shot","2PT Field Goal","In The Paint (Non-RA)","Center(C)","Less Than 8 ft.",7,77,19,1,0],["0020000359",241,2,2,56,"Missed Shot","Jump Shot","2PT Field Goal","In The Paint (Non-RA)","Center(C)","Less Than 8 ft.",7,-73,-2,1,0],["0020000359",444,4,6,55,"Missed Shot","Jump Shot","2PT Field Goal","Mid-Range","Right Side(R)","8-16 ft.",15,157,-2,1,0],["0020000359",457,4,5,42,"Made Shot","Jump Shot","2PT Field Goal","Mid-Range","Left Side(L)","8-16 ft.",8,-82,30,1,1],["0020000359",492,4,2,18,"Missed Shot","Jump Shot","2PT Field Goal","Mid-Range","Right Side(R)","8-16 ft.",15,148,36,1,0],["0020000359",507,4,0,22,"Missed Shot","Jump Shot","2PT Field Goal","In The Paint (Non-RA)","Center(C)","Less Than 8 ft.",6,62,26,1,0],["0020000369",132,2,10,12,"Made Shot","Dunk Shot","2PT Field Goal","Restricted Area","Center(C)","Less Than 8 ft.",0,-4,9,1,1],["0020000369",152,2,8,28,"Missed Shot","Jump Shot","2PT Field Goal","Mid-Range","Right Side(R)","16-24 ft.",18,180,0,1,0],["0020000369",219,2,2,14,"Made Shot","Jump Shot","2PT Field Goal","Mid-Range","Center(C)","16-24 ft.",18,1,186,1,1],["0020000382",88,1,2,56,"Made Shot","Alley Oop Layup shot","2PT Field Goal","Restricted Area","Center(C)","Less Than 8 ft.",1,18,0,1,1],["0020000382",102,1,1,26,"Made Shot","Jump Shot","2PT Field Goal","Mid-Range","Right Side(R)","8-16 ft.",8,81,15,1,1],["0020000382",179,2,7,48,"Made Shot","Jump Shot","2PT Field Goal","In The Paint (Non-RA)","Center(C)","Less Than 8 ft.",4,24,36,1,1],["0020000382",385,3,2,22,"Missed Shot","Jump Shot","2PT Field Goal","Mid-Range","Left Side(L)","16-24 ft.",20,-200,59,1,0],["0020000382",428,4,10,50,"Missed Shot","Jump Shot","2PT Field Goal","Mid-Range","Left Side(L)","8-16 ft.",9,-94,-13,1,0],["0020000382",446,4,8,44,"Missed Shot","Jump Shot","2PT Field Goal","Mid-Range","Right Side(R)","8-16 ft.",12,123,36,1,0],["0020000382",504,4,3,57,"Made Shot","Jump Shot","2PT Field Goal","In The Paint (Non-RA)","Left Side(L)","8-16 ft.",8,-79,36,1,1],["0020000382",514,4,3,4,"Missed Shot","Jump Shot","2PT Field Goal","Mid-Range","Left Side(L)","8-16 ft.",15,-149,26,1,0],["0020000395",115,2,10,33,"Made Shot","Jump Shot","2PT Field Goal","Mid-Range","Left Side(L)","16-24 ft.",17,-141,99,1,1],["0020000395",138,2,7,51,"Made Shot","Jump Shot","2PT Field Goal","Mid-Range","Right Side Center(RC)","16-24 ft.",19,146,129,1,1],["0020000395",295,3,3,33,"Made Shot","Jump Shot","2PT Field Goal","In The Paint (Non-RA)","Center(C)","Less Than 8 ft.",5,51,4,1,1],["0020000395",359,4,7,29,"Missed Shot","Jump Shot","2PT Field Goal","Mid-Range","Right Side(R)","8-16 ft.",12,87,91,1,0],["0020000395",391,4,3,48,"Missed Shot","Jump Shot","2PT Field Goal","Mid-Range","Right Side(R)","16-24 ft.",19,197,-11,1,0],["0020000408",227,2,0,46,"Missed Shot","Jump Shot","2PT Field Goal","Mid-Range","Right Side(R)","8-16 ft.",14,146,-17,1,0],["0020000408",324,3,3,42,"Made Shot","Dunk Shot","2PT Field Goal","Restricted Area","Center(C)","Less Than 8 ft.",0,3,0,1,1],["0020000408",336,3,2,50,"Made Shot","Layup Shot","2PT Field Goal","Restricted Area","Center(C)","Less Than 8 ft.",1,18,4,1,1],["0020000423",78,1,3,2,"Missed Shot","Jump Shot","2PT Field Goal","In The Paint (Non-RA)","Center(C)","8-16 ft.",12,62,112,1,0],["0020000423",97,1,1,10,"Made Shot","Layup Shot","2PT Field Goal","Restricted Area","Center(C)","Less Than 8 ft.",0,0,0,1,1],["0020000423",329,4,9,57,"Missed Shot","Jump Shot","2PT Field Goal","Mid-Range","Left Side(L)","8-16 ft.",15,-157,17,1,0],["0020000438",138,2,11,13,"Made Shot","Jump Shot","2PT Field Goal","Mid-Range","Right Side(R)","16-24 ft.",17,176,15,1,1],["0020000438",450,4,7,59,"Made Shot","Jump Shot","2PT Field Goal","Mid-Range","Right Side(R)","16-24 ft.",16,161,30,1,1],["0020000438",453,4,7,35,"Missed Shot","Layup Shot","2PT Field Goal","Restricted Area","Center(C)","Less Than 8 ft.",3,-29,9,1,0],["0020000438",473,4,5,59,"Made Shot","Jump Shot","2PT Field Goal","In The Paint (Non-RA)","Center(C)","Less Than 8 ft.",7,-79,4,1,1],["0020000474",109,1,0,25,"Made Shot","Layup Shot","2PT Field Goal","Restricted Area","Center(C)","Less Than 8 ft.",0,-1,-6,1,1],["0020000474",128,2,9,42,"Missed Shot","Jump Shot","2PT Field Goal","Mid-Range","Right Side(R)","8-16 ft.",8,89,-6,1,0],["0020000474",169,2,4,49,"Missed Shot","Jump Shot","2PT Field Goal","Mid-Range","Right Side(R)","16-24 ft.",18,182,-17,1,0],["0020000474",425,4,3,43,"Made Shot","Jump Shot","2PT Field Goal","Mid-Range","Left Side(L)","8-16 ft.",15,-157,-27,1,1],["0020000474",432,4,2,39,"Missed Shot","Jump Shot","2PT Field Goal","Mid-Range","Left Side(L)","16-24 ft.",19,-193,-17,1,0],["0020000480",85,1,1,37,"Missed Shot","Jump Shot","2PT Field Goal","Mid-Range","Center(C)","16-24 ft.",19,32,188,1,0],["0020000480",111,2,10,51,"Made Shot","Layup Shot","2PT Field Goal","Restricted Area","Center(C)","Less Than 8 ft.",0,0,0,1,1],["0020000480",203,2,0,46,"Made Shot","Jump Shot","2PT Field Goal","Mid-Range","Left Side(L)","8-16 ft.",15,-153,11,1,1],["0020000480",354,4,9,29,"Missed Shot","Jump Shot","2PT Field Goal","Mid-Range","Left Side(L)","16-24 ft.",16,-168,15,1,0],["0020000480",384,4,6,7,"Made Shot","Dunk Shot","2PT Field Goal","Restricted Area","Center(C)","Less Than 8 ft.",0,0,0,1,1],["0020000497",163,2,5,32,"Missed Shot","Jump Shot","2PT Field Goal","Mid-Range","Right Side(R)","8-16 ft.",15,104,116,1,0],["0020000497",168,2,4,48,"Missed Shot","Jump Shot","2PT Field Goal","Mid-Range","Right Side(R)","8-16 ft.",13,132,-6,1,0],["0020000497",363,4,9,9,"Made Shot","Jump Shot","2PT Field Goal","Mid-Range","Right Side(R)","8-16 ft.",15,153,-13,1,1],["0020000497",388,4,5,58,"Made Shot","Jump Shot","2PT Field Goal","Mid-Range","Right Side(R)","16-24 ft.",17,167,36,1,1],["0020000502",156,2,6,57,"Missed Shot","Jump Shot","2PT Field Goal","In The Paint (Non-RA)","Center(C)","Less Than 8 ft.",7,-79,-6,1,0],["0020000514",104,2,11,31,"Missed Shot","Jump Shot","2PT Field Goal","Mid-Range","Left Side(L)","16-24 ft.",16,-157,63,1,0],["0020000514",128,2,9,9,"Made Shot","Dunk Shot","2PT Field Goal","Restricted Area","Center(C)","Less Than 8 ft.",0,3,0,1,1],["0020000514",354,4,9,52,"Made Shot","Layup Shot","2PT Field Goal","Restricted Area","Center(C)","Less Than 8 ft.",1,18,4,1,1],["0020000537",62,1,4,48,"Missed Shot","Jump Shot","2PT Field Goal","In The Paint (Non-RA)","Center(C)","Less Than 8 ft.",4,3,42,1,0],["0020000537",160,2,6,10,"Made Shot","Running Jump Shot","2PT Field Goal","In The Paint (Non-RA)","Center(C)","Less Than 8 ft.",5,3,57,1,1],["0020000537",254,3,8,45,"Made Shot","Jump Shot","2PT Field Goal","Mid-Range","Left Side(L)","16-24 ft.",19,-193,-27,1,1],["0020000537",272,3,6,48,"Made Shot","Jump Shot","2PT Field Goal","Mid-Range","Left Side(L)","8-16 ft.",9,-94,0,1,1],["0020000537",280,3,5,34,"Missed Shot","Jump Shot","2PT Field Goal","Mid-Range","Right Side(R)","16-24 ft.",16,167,-17,1,0],["0020000537",374,4,6,41,"Missed Shot","Jump Shot","2PT Field Goal","Mid-Range","Right Side(R)","16-24 ft.",19,191,-13,1,0],["0020000551",87,1,3,13,"Missed Shot","Jump Shot","2PT Field Goal","Mid-Range","Right Side Center(RC)","16-24 ft.",16,64,148,1,0],["0020000551",231,2,2,26,"Missed Shot","Hook Shot","2PT Field Goal","In The Paint (Non-RA)","Left Side(L)","8-16 ft.",9,-77,63,1,0],["0020000551",245,2,0,47,"Missed Shot","Turnaround Jump Shot","2PT Field Goal","Mid-Range","Left Side(L)","8-16 ft.",12,-128,4,1,0],["0020000567",341,3,1,38,"Made Shot","Jump Shot","2PT Field Goal","Mid-Range","Right Side(R)","8-16 ft.",15,159,4,1,1],["0020000567",354,3,0,20,"Missed Shot","Turnaround Jump Shot","2PT Field Goal","Mid-Range","Right Side(R)","8-16 ft.",10,100,36,1,0],["0020000567",363,4,11,35,"Made Shot","Layup Shot","2PT Field Goal","Restricted Area","Center(C)","Less Than 8 ft.",0,0,0,1,1],["0020000567",394,4,7,32,"Missed Shot","Jump Shot","2PT Field Goal","Mid-Range","Right Side(R)","16-24 ft.",18,188,-6,1,0],["0020000589",113,1,0,29,"Missed Shot","Jump Shot","2PT Field Goal","Mid-Range","Right Side(R)","8-16 ft.",13,119,63,1,0],["0020000716",121,2,11,22,"Made Shot","Jump Shot","2PT Field Goal","Mid-Range","Right Side(R)","8-16 ft.",10,108,17,1,1],["0020000716",143,2,9,24,"Missed Shot","Jump Shot","2PT Field Goal","Mid-Range","Left Side(L)","8-16 ft.",14,-147,13,1,0],["0020000716",155,2,8,40,"Made Shot","Jump Shot","2PT Field Goal","Mid-Range","Right Side(R)","16-24 ft.",17,178,7,1,1],["0020000732",218,2,0,2,"Missed Shot","Jump Shot","2PT Field Goal","Mid-Range","Right Side(R)","8-16 ft.",11,110,4,1,0],["0020000732",412,4,2,1,"Made Shot","Layup Shot","2PT Field Goal","Restricted Area","Center(C)","Less Than 8 ft.",2,-16,15,1,1],["0020000745",104,1,0,53,"Missed Shot","Jump Shot","2PT Field Goal","Mid-Range","Right Side(R)","8-16 ft.",14,146,30,1,0],["0020000745",149,2,9,43,"Made Shot","Jump Shot","2PT Field Goal","Mid-Range","Left Side(L)","16-24 ft.",17,-172,9,1,1],["0020000745",151,2,9,2,"Made Shot","Jump Shot","2PT Field Goal","Mid-Range","Left Side(L)","16-24 ft.",16,-166,4,1,1],["0020000745",376,4,11,16,"Made Shot","Jump Shot","2PT Field Goal","Mid-Range","Left Side(L)","16-24 ft.",16,-145,87,1,1],["0020000745",378,4,10,36,"Missed Shot","Jump Shot","2PT Field Goal","In The Paint (Non-RA)","Center(C)","Less Than 8 ft.",5,-8,59,1,0]]}},"GameList":{"20000235":[1562,"0020000235","12/02/2000","WAS","Wizards","MIA","Heat",0,10,4,4,0,0,6,1,0,2,5],"20000313":[1562,"0020000313","12/13/2000","WAS","Wizards","PHI","76ers",1,4,2,4,0,0,5,1,2,1,2],"20000497":[1562,"0020000497","01/09/2001","WAS","Wizards","MIL","Bucks",1,4,2,4,0,0,1,0,0,0,0],"20000080":[1562,"0020000080","11/10/2000","WAS","Wizards","IND","Pacers",3,4,2,3,0,0,3,1,0,0,2],"20000272":[1562,"0020000272","12/07/2000","WAS","Wizards","MIN","Timberwolves",1,4,1,3,0,0,1,0,0,1,2],"20000551":[1562,"0020000551","01/17/2001","WAS","Wizards","NJN","Nets",2,2,0,3,0,0,2,0,0,0,0],"20000480":[1562,"0020000480","01/07/2001","WAS","Wizards","NYK","Knicks",2,6,3,5,0,0,1,0,1,2,5],"20000089":[1562,"0020000089","11/11/2000","WAS","Wizards","CLE","Cavaliers",2,8,4,7,0,0,3,0,0,0,8],"20000537":[1562,"0020000537","01/15/2001","WAS","Wizards","MIL","Bucks",1,8,3,6,0,0,3,2,1,1,7],"20000514":[1562,"0020000514","01/12/2001","WAS","Wizards","PHI","76ers",1,5,2,3,0,0,3,1,0,1,1],"20000063":[1562,"0020000063","11/08/2000","WAS","Wizards","NJN","Nets",0,2,1,2,0,0,3,0,1,0,3],"20000474":[1562,"0020000474","01/06/2001","WAS","Wizards","DAL","Mavericks",0,4,2,5,0,0,2,0,0,1,3],"20000003":[1562,"0020000003","10/31/2000","WAS","Wizards","ORL","Magic",0,6,3,3,0,0,2,0,0,1,3],"20000755":[1562,"0020000755","02/18/2001","WAS","Wizards","DEN","Nuggets",1,0,0,0,0,0,1,0,0,0,0],"20000153":[1562,"0020000153","11/21/2000","WAS","Wizards","POR","Trail Blazers",0,2,1,1,0,0,1,0,0,0,0],"20000716":[1562,"0020000716","02/13/2001","WAS","Wizards","HOU","Rockets",0,4,2,3,0,0,3,0,0,0,3],"20000732":[1562,"0020000732","02/15/2001","WAS","Wizards","SAS","Spurs",1,2,1,2,0,0,0,0,0,1,2],"20000438":[1562,"0020000438","12/31/2000","WAS","Wizards","DET","Pistons",1,6,3,4,0,0,1,0,0,0,3],"20000395":[1562,"0020000395","12/23/2000","WAS","Wizards","POR","Trail Blazers",5,10,3,5,0,0,1,0,1,1,7],"20000349":[1562,"0020000349","12/17/2000","WAS","Wizards","LAC","Clippers",0,9,3,9,0,0,5,1,0,4,5],"20000567":[1562,"0020000567","01/19/2001","WAS","Wizards","TOR","Raptors",5,4,2,4,0,0,1,0,1,2,5],"20000209":[1562,"0020000209","11/29/2000","WAS","Wizards","PHI","76ers",2,3,1,2,0,0,2,0,1,2,4],"20000328":[1562,"0020000328","12/15/2000","WAS","Wizards","CHH","Hornets",0,17,8,12,0,0,3,1,0,1,7],"20000056":[1562,"0020000056","11/07/2000","WAS","Wizards","CHI","Bulls",0,2,1,2,0,0,1,0,1,0,2],"20000200":[1562,"0020000200","11/28/2000","WAS","Wizards","ATL","Hawks",1,0,0,5,0,0,4,0,2,2,3],"20000135":[1562,"0020000135","11/18/2000","WAS","Wizards","BOS","Celtics",0,2,1,4,0,0,2,0,1,2,3],"20000359":[1562,"0020000359","12/19/2000","WAS","Wizards","SAC","Kings",1,4,2,8,0,0,1,0,0,0,4],"20000502":[1562,"0020000502","01/10/2001","WAS","Wizards","SEA","SuperSonics",0,0,0,1,0,0,1,0,0,0,0],"20000408":[1562,"0020000408","12/27/2000","WAS","Wizards","NYK","Knicks",1,4,2,3,0,0,0,0,2,0,3],"20000243":[1562,"0020000243","12/03/2000","WAS","Wizards","DET","Pistons",5,16,6,11,0,0,6,0,0,0,12],"20000262":[1562,"0020000262","12/06/2000","WAS","Wizards","LAC","Clippers",2,2,1,2,0,0,3,0,0,0,7],"20000111":[1562,"0020000111","11/15/2000","WAS","Wizards","BOS","Celtics",0,0,0,1,0,0,0,0,0,0,0],"20000017":[1562,"0020000017","11/01/2000","WAS","Wizards","CHH","Hornets",0,4,1,1,0,0,3,0,0,1,3],"20000745":[1562,"0020000745","02/17/2001","WAS","Wizards","DAL","Mavericks",2,6,3,5,0,0,0,0,0,0,2],"20000369":[1562,"0020000369","12/20/2000","WAS","Wizards","VAN","Grizzlies",1,4,2,3,0,0,0,0,0,0,1],"20000175":[1562,"0020000175","11/24/2000","WAS","Wizards","IND","Pacers",0,5,2,4,0,0,3,0,0,0,1],"20000037":[1562,"0020000037","11/04/2000","WAS","Wizards","TOR","Raptors",1,14,4,8,0,0,4,2,0,1,2],"20000119":[1562,"0020000119","11/16/2000","WAS","Wizards","SAS","Spurs",0,4,2,4,0,0,1,0,0,0,1],"20000382":[1562,"0020000382","12/22/2000","WAS","Wizards","SEA","SuperSonics",0,9,4,8,0,0,4,0,0,1,3],"20000589":[1562,"0020000589","01/23/2001","WAS","Wizards","CHH","Hornets",2,0,0,1,0,0,1,0,0,0,0],"20000287":[1562,"0020000287","12/09/2000","WAS","Wizards","MIL","Bucks",0,4,2,3,0,0,1,0,0,0,1],"20000763":[1562,"0020000763","02/20/2001","WAS","Wizards","VAN","Grizzlies",0,0,0,0,0,0,0,0,0,0,0],"20000029":[1562,"0020000029","11/03/2000","WAS","Wizards","NYK","Knicks",0,0,0,0,0,0,0,0,0,0,0],"20000423":[1562,"0020000423","12/29/2000","WAS","Wizards","MIA","Heat",1,2,1,3,0,0,3,0,0,1,2],"20000183":[1562,"0020000183","11/25/2000","WAS","Wizards","MIL","Bucks",1,10,3,5,0,0,3,1,0,2,2]},"data":[28.0,45,3,15.7,2.0,3.9,0.511,0.0,0.0,0.0,0.8,1.0,0.8,0.9,2.0,2.9,0.7,0.3,0.2,1.0,2.1,4.8],"rank":{"PerGame":[null,null,null,null,null,null,null,null,null,null,null,null,null,null,null,null,null,null,null],"Totals":[283,279,294,null,295,368,null,277,286,null,233,270,266,298,302,236,258,285,288]},"team":"WAS"}},"headerRank":["RANK_PG_MIN","RANK_PG_FGM","RANK_PG_FGA","RANK_FG_PCT","RANK_PG_FG3M","RANK_PG_FG3A","RANK_FG3_PCT","RANK_PG_FTM","RANK_PG_FTA","RANK_FT_PCT","RANK_PG_OREB","RANK_PG_DREB","RANK_PG_REB","RANK_PG_AST","RANK_PG_STL","RANK_PG_BLK","RANK_PG_TOV","RANK_PG_PTS","RANK_PG_EFF"]}}